Workbook
Name 대공종: [1]!표1[대공종]
Name 대분류: [1]!표30[대분류]
Name 소공종: [1]!표8[소공종]
Name 처리분류: [1]!표20[처리분류]

Sheet 📖 README
A1: 플랜트구매품질팀 통합관리 대시보드 - Excel 입력 양식
A3: 사용 방법
A4: 1. 아래 시트탭의 각 시트(프로젝트_현황 / 프로젝트_구매품질 실적 / 프로젝트_NCR처리현황 / PQAN / TPA_목록 / TPA_집행현황 / TPA_월별대금청구현황 / 인력운영_현황 / 인력운영_세부내역 / 출장현황 / 주요현안)에 데이터를 입력합니다.
A5: 2. 1행의 컬럼명(헤더)은 절대 변경하지 마세요. 시트명도 그대로 유지해야 합니다.
A6: 3. 데이터는 2행부터 입력합니다. 컬럼 순서는 자유롭게 변경해도 됩니다.
A7: 4. 작성이 끝나면 이 파일을 저장하고, 대시보드 HTML을 열어 'Excel 업로드' 버튼으로 불러옵니다.
A8: 5. 모든 KPI · 표 · 차트 · 조직도 · PQAN · TPA가 자동으로 채워집니다.
A10: 주요 입력 규칙
A11: • 프로젝트_구매품질 실적 시트: 단계 컬럼(MR/TBE/PO/PIM/IRC)에 '완료'를 입력하면 100%로 처리됩니다.
A12: • TPA_집행현황 시트: 금액은 USD 또는 KRW 중 한쪽만 입력해도 환율로 자동 환산됩니다 (USD 단위, 백만 단위 아님).
A13: • 단계 컬럼: 'Active', 'Mechanical Completion', 'Bid' 중 하나로 입력해주세요.
A14: • Mechanical Completion 상태 프로젝트는 TPA Warning 로직에서 자동 제외됩니다.
... A36: • 가중 진척률 = (각 단계 진행률 × 가중치)의 합

Sheet 프로젝트_현황
A1: 프로젝트 | B1: HDEC 계약고 (USD) | C1: 전체 계약고 (USD) | D1: HDEC 계약고 (KRW) | E1: 전체 계약고 (KRW) | F1: 발주처 | G1: 국가 | H1: PD | I1: PQCM | J1: 단계 | K1: 공정률 | L1: 비고
A2: MIP6 | B2: 1484 | C2: 1484 | F2: Aramco | G2: 사우디아라비아 | H2: - | I2: - | J2: Mechanical Completion | K2: 1
A3: SM12 | B3: 1318 | C3: 1354 | F3: Aramco | G3: 사우디아라비아 | H3: 정준택 상무 | I3: 장동철 책임 | J3: Active | K3: 0.9997
A4: IBRU | B4: 1814 | C4: 3778 | F4: BOC | G4: 이라크 | H4: 정태수 소장 | I4: - | J4: Mechanical Completion | K4: 1
A5: SHN1 | D5: 2389100 | E5: 5436800 | F5: S-Oil | G5: 대한민국 | H5: 이현영 실장 | I5: 이해석 책임 | J5: Active | K5: 0.9628
A6: ALOM | B6: 584 | C6: 730 | F6: Hyenco | G6: 알제리 | H6: 정민권 소장 | I6: 윤희수 책임 | J6: Active | K6: 0.598
A7: VEQU | B7: 952 | C7: 1178 | F7: EVN | G7: 베트남 | H7: 이윤석 소장 | I7: 윤희수 책임 | J7: Active | K7: 0.9915
A8: STA4 | B8: 2136 | C8: 2136 | F8: satorp | G8: 사우디아라비아 | H8: 임영빈 상무 | I8: 최우석 책임 | J8: Active | K8: 0.8831
A9: SAC2 | B9: 1184 | C9: 2369 | F9: Aramco | G9: 사우디아라비아 | H9: 김형철 실장 | I9: 최종현 책임 | J9: Active | K9: 0.7258
A10: CSSP | B10: 3160 | C10: 3160 | F10: TotalEnergies | G10: 이라크 | H10: 박수철 상무 | I10: 정진우 책임 | J10: Active | K10: 0.0754
A11: PNG1 | B11: 1600 | C11: 4000 | F11: ExxonMobil | G11: 파푸아뉴기니 | H11: 최성식 팀장 | I11: 강태준 책임 | J11: Active | K11: 0
A12: ALSM | B12: 5800 | C12: 5800 | F12: HPLS | G12: 미국 | H12: 백철욱 상무 | I12: 강태준 책임 | J12: Bid | K12: 0

Sheet 프로젝트_구매품질 실적
A1: 프로젝트 | B1: MR_Total | C1: MR_Done | D1: TBE_Total | E1: TBE_Done | F1: PO_Total | G1: PO_Done | H1: PIM_Total | I1: PIM_Done | J1: IRC_100%_Total | K1: IRC_100%_Done | L1: NCR_Total | M1: NCR_Done
A2: MIP6 | B2: 완료 | C2: 완료 | D2: 완료 | E2: 완료 | F2: 200 | G2: 200 | H2: 197 | I2: 197 | J2: 397 | K2: 397 | L2: 55 | M2: 55
A3: SM12 | B3: 완료 | C3: 완료 | D3: 완료 | E3: 완료 | F3: 150 | G3: 150 | H3: 167 | I3: 167 | J3: 353 | K3: 350 | L3: 80 | M3: 80
A4: IBRU | B4: 완료 | C4: 완료 | D4: 완료 | E4: 완료 | F4: 124 | G4: 124 | H4: 45 | I4: 45 | J4: 124 | K4: 124 | L4: 7 | M4: 7
A5: SHN1 | B5: 완료 | C5: 완료 | D5: 완료 | E5: 완료 | F5: 24 | G5: 24 | H5: 17 | I5: 17 | J5: 40 | K5: 35 | L5: 15 | M5: 15
A6: ALOM | B6: 완료 | C6: 완료 | D6: 완료 | E6: 완료 | F6: 74 | G6: 74 | H6: 28 | I6: 28 | J6: 74 | K6: 50 | L6: 16 | M6: 16
A7: VEQU | B7: 완료 | C7: 완료 | D7: 완료 | E7: 완료 | F7: 96 | G7: 96 | H7: 37 | I7: 37 | J7: 96 | K7: 95 | L7: 9 | M7: 9
A8: STA4 | B8: 완료 | C8: 완료 | D8: 완료 | E8: 완료 | F8: 159 | G8: 159 | H8: 100 | I8: 97 | J8: 121 | K8: 53 | L8: 53 | M8: 44
A9: SAC2 | B9: 완료 | C9: 완료 | D9: 완료 | E9: 완료 | F9: 93 | G9: 93 | H9: 62 | I9: 59 | J9: 89 | K9: 22 | L9: 8 | M9: 8
A10: CSSP | B10: 148 | C10: 89 | D10: 148 | E10: 8 | F10: 148 | G10: 1 | H10: 57 | I10: 0 | J10: 148 | K10: 0 | L10: 0 | M10: 0
A11: PNG1 | B11: 30 | C11: 11 | D11: 30 | E11: 5 | F11: 30 | G11: 2 | H11: 17 | I11: 0 | J11: 30 | K11: 0 | L11: 0 | M11: 0
A12: ALSM | B12: 미정 | C12: 미정 | D12: 미정 | E12: 미정 | F12: 미정 | G12: 미정 | H12: 미정 | I12: 미정 | J12: 미정 | K12: 미정 | L12: 미정 | M12: 미정

Sheet 프로젝트_NCR처리현황
A1: 작업공종 대공종 | B1: 작업공종 중공종 | C1: 작업공종 소공종 | D1: 근본원인 대분류 | E1: 근본원인 중분류 | F1: 처리분류 | G1: 프로젝트 | H1: Issued by | I1: NCR No. | J1: PO No. | K1: 공종 | L1: 품목 | M1: Main Vendor | N1: Sub Vendor | O1: Issue Date | P1: Due Date | Q1: Closed Date | R1: NCR Description | S1: Action Status
A2: 기계.설비 | B2: 일반기계_고정.회전 | C2: 자재불량 | D2: 자재 | E2: 도면, 기술시방서 요건과 상이한 제작 | F2: 현상태사용 | G2: MIP6 | H2: 현대건설 | I2: NCR-OOK-MS019-001 | J2: MS019 | K2: MS | L2: Dehydrator & Desalter_HIC Plate | M2: Cameron | N2: Voestalpine | O2: 43874 | P2: 43931 | Q2: 43924 | R2: Specimens of plate 184477 produced from heat no° 721340 didn´t pass succesfully HIC test. Mesured CTR mean value = 5,86% ≥ max. CTR allowed 3%
A3: 기계.설비 | B3: 일반기계_고정.회전 | C3: 자재불량 | D3: 자재 | E3: 도면, 기술시방서 요건과 상이한 제작 | F3: 폐기 | G3: MIP6 | H3: 현대건설 | I3: NCR-OOK-MS020-001 | J3: MS020 | K3: MS | L3: Water Oil Separator_HIC Plate | M3: NAMEL | N3: Voestalpine | O3: 43899 | P3: 43981 | Q3: 43913 | R3: One plate width is not suitable to ordered plate width. It was found during mill's internal monitoring.
A4: 기계.설비 | B4: 일반기계_고정.회전 | C4: 자재불량 | D4: 자재 | E4: 도면, 기술시방서 요건과 상이한 제작 | F4: 폐기 | G4: MIP6 | H4: 현대건설 | I4: NCR-OOK-MS021-001 | J4: MS021 | K4: MS | L4: LPPT_HIC Plate | M4: TSM | N4: Voestalpine | O4: 43910 | P4: 43982 | Q4: 44015 | R4: Specimens of plate 187759 produced from heat no° 916271 didn´t pass succesfully HIC test. Mesured CLR mean value = 11,67% ≥ max. CLR allowed 10%
A5: 기계.설비 | B5: 일반기계_고정.회전 | C5: 자재불량 | D5: 자재 | E5: 도면, 기술시방서 요건과 상이한 제작 | F5: 폐기 | G5: MIP6 | H5: 현대건설 | I5: NCR-OOK-MS019-002 | J5: MS019 | K5: MS | L5: Dehydrator & Desalter_HIC Plate | M5: Cameron | N5: Voestalpine | O5: 43937 | P5: 44012 | Q5: 44008 | R5: Specimens of plate 195575 produced from heat no° 722639 does not meet requirements max. HIC figures. Mesured CT value exceed max. CTR allowed (3%)
A6: 기계.설비 | B6: 일반기계_고정.회전 | C6: 자재불량 | D6: 자재 | E6: 도면, 기술시방서 요건과 상이한 제작 | F6: 폐기 | G6: MIP6 | H6: 현대건설 | I6: NCR-OOK-MS021-002 | J6: MS021 | K6: MS | L6: LPPT_HIC Plate | M6: TSM | N6: Voestalpine | O6: 43958 | P6: 44074 | Q6: 44015 | R6: Applicable 01-SAMMS-016 (Jan 2018) requires following: Stepwise cracking in which the calculated average CLR of any of the specimen exceed 10%, and/or CTR of any of the specimens exceeds 3%, is not acceptable. The plate that failed the test, rejected.
A7: 기계.설비 | B7: 일반기계_고정.회전 | C7: 자재불량 | D7: 자재 | E7: 도면, 기술시방서 요건과 상이한 제작 | F7: 폐기 | G7: MIP6 | H7: 현대건설 | I7: NCR-OOK-MS021-003 | J7: MS021 | K7: MS | L7: LPPT_HIC Plate | M7: TSM | N7: Voestalpine | O7: 43958 | P7: 44074 | Q7: 44015 | R7: Applicable 01-SAMMS-016 (Jan 2018) requires following: Stepwise cracking in which the calculated average CLR exceed 10% average from 3 specimens, and/or CTR exceeds 3% average from 3 specimens, is not acceptable. The plate that failed the test, rejected.
A8: 전기 | B8: 급.배전설비 | C8: 자재불량 | D8: 자재 | E8: 도면, 기술시방서 요건과 상이한 제작 | F8: 수리 | G8: MIP6 | H8: 현대건설 | I8: NCR-OOK-EL001-001 | J8: EL001 | K8: EL | L8: 230KV GIS | M8: ABB Switzerland | N8: - | O8: 44083 | P8: 44155 | Q8: 44139 | R8: The power frequency withstand voltage test of circuit breaker phase 1HC300153594 in close position at 460Kv (ITP step C1-9) was failed immediately after reaching 460kV. Hitachi-ABB to investigate, propose a corrective action and notify for a new test after correction.
A9: 기계.설비 | B9: 기타 | C9: 손상 | D9: 자재 | E9: 품목의 결함, 손상 및 제작불량 | F9: 폐기 | G9: MIP6 | H9: 현대건설 | I9: NCR-OOK-PI001-001 | J9: PI001 | K9: PI | L9: CS SMLS PIPE | M9: TPCO | N9: - | O9: 44091 | P9: 44127 | Q9: 44119 | R9: During Visual Inspection of normalized pipes furnished to Ident. Code I164201658 on 02~03-Sep-2020, TPI Inspector found Heat 609124 and Hdea 609125 pipes had different-depth dents in the body. As ASTM A106 doesn't specify definite acceptance criteria on dents, TPI inspector cited API5L relevant requirements as the acceptance limits. After measuring the flat-bottom dent depth, TPI inspector confirmed that two Heat 609124 pipes and two Heat 609125 pipes had severe dents exceeding 6.4mm. The four defective pipes were already rejected. Even so, it is not permitted that each pipe body had acceptable-depth dents.
A10: 기계.설비 | B10: 일반기계_고정.회전 | C10: 기타 | D10: 자재 | E10: 서류의 결함, 미비 | F10: 재작업 | G10: MIP6 | H10: 현대건설 | I10: NCR-OOK-MS020-002 | J10: MS020 | K10: MS | L10: Water Oil Separator PKG | M10: NOVEL ARABIA MIDDLE EAST LTD | N10: - | O10: 44249 | P10: 44316 | Q10: 44308 | R10: Receiving inspection below nonconformities on BOM Item # 222 (Nozzle N9A/B) Nozzle Pipe 10" Sch 80 SA 106 Gr.B Pipe (MTC#590004595-10 Rev.1)
A11: 기계.설비 | B11: 일반기계_고정.회전 | C11: 자재불량 | D11: 자재 | E11: 도면, 기술시방서 요건과 상이한 제작 | F11: 폐기 | G11: MIP6 | H11: 현대건설 | I11: NCR-OOK-MS020-003 | J11: MS020 | K11: MS | L11: Water Oil Separator PKG | M11: NOVEL ARABIA MIDDLE EAST LTD | N11: - | O11: 44249 | P11: 44438 | Q11: 44383 | R11: Receiving inspection observed below nozzles lengths discrepancy from approved drawing VD-MS020-004 Rev.0
A12: 기계.설비 | B12: 일반기계_고정.회전 | C12: 기타 | D12: 자재 | E12: 도면, 기술시방서 요건과 상이한 제작 | F12: 현상태사용 | G12: MIP6 | H12: 현대건설 | I12: NCR-OOK-MS013-001 | J12: MS013 | K12: MS | L12: N2 Generation PKG | M12: HADETEC | N12: TANKBOUW | O12: 44284 | P12: 44316 | Q12: 44308 | R12: The 2" Nozzle welds on the pre-filter were performed using SMAW. This is not as per the approved WPS/PQR. It should be welded with GTAW at this is the only option as per weld map.
A13: 기계.설비 | B13: 일반기계_고정.회전 | C13: 누수 | D13: 자재 | E13: 품목의 결함, 손상 및 제작불량 | F13: 수리 | G13: MIP6 | H13: 현대건설 | I13: NCR-OOK-MR026-001 | J13: MR026 | K13: MR | L13: Water Injection Pump | M13: TRILLIUM PUMPS ITALY SRL | N13: - | O13: 44294 | P13: 44657 | Q13: 44491 | R13: An Heavy Leakage around the Mechanical Seal Area of Drive End was detected during Performace Test close to the completion. Trillum decide to stop the pump in order to investigate the matter and avoiding damages on internal parts. Trillium together with John Crane (seal supplier) will investigate about the causes of the failure, and inform accordingly. Some pictures separately attached.
... A16: 기계.설비 | B16: 기타 | C16: 자재불량 | D16: 자재 | E16: 도면, 기술시방서 요건과 상이한 제작 | F16: 현상태사용 | G16: MIP6 | H16: 현대건설 | I16: NCR-OOK-PI009-001 | J16: PI009 | K16: PI | L16: RTR Piping | M16: Future Pipe Industry | N16: - | O16: 44348 | P16: 44531 | Q16: 44526 | R16: FPI manufactured RTR Pipes and Fittings with different ASTM codes application compared to BM description. During Final Inspection, it is observed that below items were applied different ASTM codes
A17: 기계.설비 | B17: 일반기계_고정.회전 | C17: 자재불량 | D17: 자재 | E17: 도면, 기술시방서 요건과 상이한 제작 | F17: 폐기 | G17: MIP6 | H17: 현대건설 | I17: NCR-OOK-MS001-001 | J17: MS001 | K17: MS | L17: Vessel I_Dish Head | M17: Al Zamil | N17: Wuhan Linmei | O17: 44438 | P17: 44611 | Q17: 2021-08-31 2021-10-26 2021-11-12 | R17: For Head No.Y210520-1 (Tag No.M96-D-0319 / Q’ty :1EA / SA516-70 HIC), non-conformance was found as following (Attachment#1–GAD): 1. Out of Tolerance for dinmension of Height - Required height : 583.4± per approved drawing LMWM-2020-2396-08/Rev.2. - Actual height : 592mm 2. Out of Tolerance for Plate thickness - Required minimum thickness is 9mm per approved drawing ZHI-ENG-SKT-2396-08_01/Rev.0 - Measured thickness at the location of the knuckle area : min. 8.61
A18: 기계.설비 | B18: 일반기계_고정.회전 | C18: 자재불량 | D18: 자재 | E18: 도면, 기술시방서 요건과 상이한 제작 | F18: 수리 | G18: MIP6 | H18: 현대건설 | I18: NCR-OOK-MR001-001 | J18: MR001 | K18: MR | L18: Centrifugal Compressor | M18: GESA | N18: NUOVO PIGNONE | O18: 44519 | P18: 44610 | Q18: 44658 | R18: [Issue #1] The first issue has been found during machining on DGS housing. As per below snapshot the circular shape red highlighted, has been executed out of center around 2 mm and ENG disposition is: repair by weld and machining to restore as per drawing. [Issue #2] In the same casing we found an additional issue, tracked in our system with M2136025: 4 threaded holes have been machined out of center
A19: 기계.설비 | B19: 일반기계_고정.회전 | C19: 미시공 | D19: 자재 | E19: 기타 | F19: 재작업 | G19: MIP6 | H19: 현대건설 | I19: NCR-OOK-MR026-003 | J19: MR026 | K19: MR | L19: Water Injection Pump | M19: TRILLIUM PUMPS ITALY SRL | N19: - | O19: 44519 | P19: 44819 | Q19: 44820 | R19: During the Final Inspection / Visual and Dimensional check(ITP step P_0036779 / 01 to 03), it was found that double language English was not applied to WARNING LABEL on junction box inside, only English language applied.
A20: 기계.설비 | B20: 일반기계_고정.회전 | C20: 누수 | D20: 자재 | E20: 취급관리 미흡, 취급 손상 | F20: 재작업 | G20: MIP6 | H20: 현대건설 | I20: NCR-OOK-MR024-001 | J20: MR024 | K20: MR | L20: WIP(OWSF) | M20: AES Arabia | N20: - | O20: 44623 | P20: 44764 | Q20: 44644 | R20: During the receiving inspection - 24 inch pneumatic actuated valve tag # M97-AOV-0448 found hydraulic oil leaked
A21: 기계.설비 | B21: 일반기계_고정.회전 | C21: 기타 | D21: 자재 | E21: 도면, 기술시방서 요건과 상이한 제작 | F21: 재작업 | G21: MIP6 | H21: 현대건설 | I21: NCR-OOK-MS001-002 | J21: MS001 | K21: MS | L21: Vessel I | M21: Al Zamil | N21: - | O21: 44697 | P21: 44752 | Q21: 44739 | R21: Violation of approved WPS was found that welding was performing without preheating on Vessel (Tag No.M96-D-0319 / Nozzle “N2”).
A22: 기계.설비 | B22: 일반기계_고정.회전 | C22: 손상 | D22: 자재 | E22: 품목의 결함, 손상 및 제작불량 | F22: 현상태사용 | G22: MIP6 | H22: 현대건설 | I22: NCR-OOK-MS020-004 | J22: MS020 | K22: MS | L22: Water Oil Separator PKG | M22: NOVEL ARABIA MIDDLE EAST LTD | N22: - | O22: 44726 | P22: 44722 | Q22: 44762 | R22: During shop surveillance inspection, surface deformation (refer to below photos) observed on the roller holding long seam welds (LS # 1B, 7B, 17B & 23B) and its opposite roller side also for the equipment tag # M95-D-0210.
A23: 기계.설비 | B23: 일반기계_고정.회전 | C23: 자재불량 | D23: 자재 | E23: 도면, 기술시방서 요건과 상이한 제작 | F23: 수리 | G23: MIP6 | H23: 현대건설 | I23: NCR-OOK-MR024-002 | J23: MR024 | K23: MR | L23: OWSF(WIP)_Pump | M23: AES Arabia | N23: Flowserve Worthington s.r.l | O23: 44763 | P23: 44895 | Q23: 44830 | R23: Flowserve Worthignton machined two unnecessary holes on drive end and non-drive end sides of casings of items, M97-G-0002B and M97-G-0002C. Holes diameter is ½” NPT for all 4 holes. Meanwhile, the holes are not drilled on Tag. M97-G-0002A and M97-G-0002D.
A24: 전기 | B24: 급.배전설비 | C24: 미시공 | D24: 자재 | E24: 기타 | F24: 재작업 | G24: MIP6 | H24: 현대건설 | I24: NCR-OOK-EL008-001 | J24: EL008 | K24: EL | L24: LV SWGR/MCC, Cablebus (M97-101-SG-001) | M24: WESCOSA | N24: - | O24: 44803 | P24: 44974 | Q24: 45043 | R24: 04 Ea. PT disconnect switches are missing in 480V, 3200A, 3PH, 60HZ, 85kA―C Low Voltage Switchgear (tag# M97-101-SG-001) This issue was highlighted in the punch list issued at the time of FAT. As per vendor, the missing material will be fixed at site. Due to urgency of the delivery, the SWGR tag# M97-101-SG-001 is agreed to be shipped without 04 Ea disconnect switches. This NCR is issued on the advice of Saudi Aramco in order to follow up hte closure of the comment in the attached punch list with regard to the 04Ea missing disconnect swiches. The NCR will be closed by HDEC once the 04Ea missing disconnect swiches will be fixed at site by WESCOSA.
A25: 기계.설비 | B25: 일반기계_고정.회전 | C25: 기타 | D25: 자재 | E25: 도면, 기술시방서 요건과 상이한 제작 | F25: 재작업 | G25: MIP6 | H25: 현대건설 | I25: NCR-OOK-MS021-1-002 | J25: MS021-1 | K25: MS | L25: LPPT_M95-D-0200 | M25: ZAMIL PROCESS EQUIPMENT CO. LTD. | N25: - | O25: 44832 | P25: 44995 | Q25: 44944 | R25: The blasting and painting activities of internal surface (primer) was completed on 28th June 2022. The concecutive coating for successive coating (intermediate layer) was not performed within prescribed duration. It is not fulfilling the maximum over coating period requirement of data sheet of Paint Hempadur 85671 & SAES-H-101V.
A26: 기계.설비 | B26: 일반기계_고정.회전 | C26: 기타 | D26: 시험.검사 | E26: 절차서, 지침서의 미준수 | F26: 재작업 | G26: MIP6 | H26: 현대건설 | I26: NCR-OOK-MR016-001 | J26: MR016 | K26: MR | L26: Oily Water Treatment Package _API Three Way Flow Splitter and vessel M97-D-0112 A/B M97-D-0116 A/B | M26: DS21 | N26: ABJ | O26: 44852 | P26: 44926 | Q26: 44945 | R26: During the review of MTC, it was found that 1) For free issued material plates, as per 32-SAMSS-004 – Paragraph 12.1.12 required tensile testing is at ½ t location, in provided MTC’s tests are performed at ¼ t Location. MTC’S attached. 2) For free issued material plates (provided MTC’s specified only 2 cycles) as per 32-SAMSS-004- 12.1.9 (Two PWHT cycles to account for future repairs and/or alterations.) MTC’S attached.
A27: 전기 | B27: 제어설비 | C27: 미시공 | D27: 자재 | E27: 기타 | F27: 재작업 | G27: MIP6 | H27: 현대건설 | I27: NCR-OOK-EL003-001 | J27: EL003 | K27: EL | L27: Control and Protective Panel | M27: Hitachi Energy Ltd. | N27: - | O27: 44907 | P27: 45088 | Q27: 45063 | R27: Metrosils, Series, Shunt (Variable, Stabilizing, Non Linear) Resistors are not installed on all High Impedance Protection Panels. As per response received, the contractor HDEC will finalize the relay setting calculation and it will be shared with Vendor for procuremment of Metrosils, Series, Shunt (Variable, Stabilizing, Non Linear) Resistors. Due to urgency of the delivery of the material; the relay & protection panel (with tags as mentione below) will be dispatched without these metrosils and resistors, and it was agreed among HDEC & Hitachi that it will be fixed at site. The same information was shared with Saudi Aramco and their concurrence was obtained. This NCR is issued on the advice of Saudi Aramco in order to follow up the installation of missing metrosils & resistors in panels at site. The NCR will be closed by HDEC once the missing metrosils & resistors will be fixed in all panels (with tags as metioned below) at site. Panels Affected: M97-101-PRP-011/ 012/ 013/ 014/ 015/ 016/ 017/ 018/ 019/ 020/ 021/ 022/ 023/ 024/ 025/ 026/ 027/ 028/ 029/ 030/ 032 (total 21 Each) Requirements/
A28: 전기 | B28: 제어설비 | C28: 미시공 | D28: 자재 | E28: 기타 | F28: 재작업 | G28: MIP6 | H28: 현대건설 | I28: NCR-OOK-EL003-002 | J28: EL003 | K28: EL | L28: Control and Protective Panel | M28: Hitachi Energy Ltd. | N28: - | O28: 44907 | P28: 45088 | Q28: 44911 | R28: The 94 Trip Relay provided in the relay & protection panels is not furnished with two spare NC contacts as required by clause 13.3.3 of 16-SAMSS-514. Since no waiver was obtained by vendor Hitachi from CSD, therefore vendor shall provide these two spare NC contacts for each 94 Trip relay. Due to urgency of the delivery of the material; the relay & protection panel be dispatched without these two spare NC contacts. As confirmed by HDEC– this matter will be addressed and closed at site under contractor responsibility and HDEC will ensure full compliance to clause 13.3.3 of 16-SAMSS-514 for each panel having 94 Trip relay. The same information was shared with Saudi Aramco and their concurrence was obtained. This NCR is issued on the advice of Saudi Aramco in order to follow up the closure of this comment at site. The NCR will be closed by HDEC once compliance to clause 13.3.3 of 16-SAMSS-514 is ensured i.e. two spare NC contacts are added for each 94 Trip Relay. Panels Affected: All panels with 94 Trip Relay Installed
A29: 전기 | B29: 제어설비 | C29: 미시공 | D29: 자재 | E29: 기타 | F29: 재작업 | G29: MIP6 | H29: 현대건설 | I29: NCR-OOK-EL009-001 | J29: EL009 | K29: EL | L29: Power System Automation | M29: Schweitzer Engineering Laboratories | N29: TIEPCO | O29: 44911 | P29: 45063 | Q29: 45625 | R29: During the Final inspection of PSA panels at Sub-vendor, some punch p oints were not rectified by main vendor and sub-vendor. As per section 9.8 of SAEP-1151 requirement, contractor shall not release material with punch list items unless approval is obtained from company representative. Hence it was agreed with company representative to issue INCR for outstanding points along with conditional release. The punch list is attached along with this INCR. The affected panels are: M97-101-PSA-001 M97-107-PSA-001
... A38: 기계.설비 | B38: 일반기계_고정.회전 | C38: 기타 | D38: 시험.검사 | E38: 검사, 시험의 미시행 또는 미흡 | F38: 재작업 | G38: MIP6 | H38: 현대건설 | I38: NCR-OOK-MR005-001 | J38: MR005 | K38: MR | L38: API PUMP(BB) | M38: Sulzer Pump | N38: Sulzer Pump UK | O38: 44998 | P38: 45202 | Q38: 45117 | R38: For UK-IN-052 Rev.2 & UK-IN-053 Rev.1, inspection was proceed with only Vendor
A39: 기계.설비 | B39: 일반기계_고정.회전 | C39: 미시공 | D39: 자재 | E39: 기타 | F39: 재작업 | G39: MIP6 | H39: 현대건설 | I39: NCR-OOK-MR012-001 | J39: MR012 | K39: MR | L39: (M97-G-0767)_FIRE WATER PUMP | M39: Sulzer Pump | N39: Sulzer Pump KSA | O39: 45299 | P39: 2024-06-31 | Q39: 45369 | R39: 1. As per 34-SAMSS-831 section 11, An identification tag or nameplate of 316 stainless steel shall be attached securely to the equipment with SS or Monel fasteners. The tag shall be marked with raised alpha-numeric or die stamped with the proper information, The tag or nameplate shall be located so that the information can be read after installation of the equipment or components. But it was found that Saudi Aramco PO number not mentioned in the skid name plate. 2. LCS internal wiring shall be tagged as required by SAES-J-902, section16.1.1. All wiring shall be tagged at each end. Each wire tag shall have two labels. The first label (closest to the end of the wire) shall identify the terminal number to which the wire is physically connected. The other label shall be the terminal number of the connection of the opposite end of the wire.
A40: 기계.설비 | B40: 일반기계_고정.회전 | C40: 자재불량 | D40: 자재 | E40: 품목의 결함, 손상 및 제작불량 | F40: 재작업 | G40: MIP6 | H40: 현대건설 | I40: NCR-OOK-MS006-001 | J40: MS006 | K40: MS | L40: S&T Heat Exchanger | M40: ZPEC | N40: - | O40: 45302 | P40: 45415 | Q40: 45323 | R40: During M95-E-0205A (after PWHT) tube side hydrostatic test it is observed that channel insulation ring ISR#01 cleats are cut from near the ring and the cleats falling at orientation 87.5°, 110°, 177.5°, 200°, 267.5°, 290°, 312.5° are deformed. Reason for cutting and deforming cleats are found to be bolt tightening access requirement for hydrostatic test preparation. Same deformation of cleats are observed on M95-E-0205B channel insulation ring ISR#01 which has been utilized for M95-E-0205A/B spare bundle tube side hydrostatic test.
A41: 기계.설비 | B41: 일반기계_고정.회전 | C41: 자재불량 | D41: 자재 | E41: 식별, 추적관리 미흡 | F41: 현상태사용 | G41: MIP6 | H41: 현대건설 | I41: NCR-OOK-MS008-001 | J41: MS008 | K41: MS | L41: Electrical Heater | M41: Chromaolx | N41: - | O41: 45314 | P41: 45380 | Q41: 45441 | R41: 8" SCH 80 SMLS, 1/2"[12.7mm] WALL Tee was seen with manufacturer’s identification markings/Material B/SB564 as seen. The stamping of material type and grade did not match that seen on the supporting MTC reflecting B/SB366. The required material is B/SB366 not B/SB564.
A42: 기계.설비 | B42: 일반기계_고정.회전 | C42: 자재불량 | D42: 자재 | E42: 식별, 추적관리 미흡 | F42: 현상태사용 | G42: MIP6 | H42: 현대건설 | I42: NCR-OOK-MS008-002 | J42: MS008 | K42: MS | L42: Electrical Heater | M42: Chromaolx | N42: - | O42: 45314 | P42: 45502 | Q42: 45441 | R42: The followed flanges are need to be re-stamped because it is not matched with the required material. 8" 600# RFWN, SCH 80 BORE : 6 pcs 2" 600# RFLWN : 4 pcs 8" 600# BLIND RF : 2 pcs 6” 2500# RTJ HB LWN : 4 pcs 2” 2500# RTJ RFLWN : 2 pcs The required marking: N08810 The actual marking: N08800 or N08811
A43: 기계.설비 | B43: 일반기계_고정.회전 | C43: 미시공 | D43: 자재 | E43: 기타 | F43: 재작업 | G43: MIP6 | H43: 현대건설 | I43: NCR-OOK-MR005(SSPC)-001 | J43: MR005 | K43: MR | L43: Hot Oil Circulation Pump Tag # M95-G-0700 A/B/C | M43: SULZER SAUDI PUMP COMPANY LIMITED | N43: - | O43: 45341 | P43: 45522 | Q43: 45593 | R43: During the final inspection of the Hot Oil Circulation Pump assembly (Tag # M95-G-0700 A/B/C), auxiliary piping (plan 23), temperature indicators (TI/TW), and associated piping, gaskets, and fasteners were found unsecured and not installed.
A44: 기계.설비 | B44: 일반기계_고정.회전 | C44: 자재불량 | D44: 자재 | E44: 도면, 기술시방서 요건과 상이한 제작 | F44: 재작업 | G44: MIP6 | H44: 현대건설 | I44: NCR-OOK-MR005(SSPC)-002 | J44: MR005 | K44: MR | L44: Hot Oil Circulation Pump Tag # M95-G-0700 A/B/C | M44: SULZER SAUDI PUMP COMPANY LIMITED | N44: - | O44: 45341 | P44: 45522 | Q44: 45635 | R44: During the final inspection of the pump assembly Hot Oil Circulation Pump Tag # M95-G-0700 A/B/C, a discrepancy was identified with the coating system applied to the casing washers. As per MR # MIP6-MR-MR-005 Rev C, Para 1.27.4, Coating system (M95-A-HE-100001) and specification SAES-H-001, and Coating system Map # M95-A-HE-100001 Rev A1, para 6.4 Fasteners (For pressure retaining equipment/piping, excluding structural fasteners), all fasteners, including casing washers, should be coated with ceramic fluoropolymer as per 09-SAMSS-107. However, during the inspection, it was found that the casing washers in the actual pump assembly were not PTFE coated.
A45: 기계.설비 | B45: 일반기계_고정.회전 | C45: 기타 | D45: 자재 | E45: 도면, 기술시방서 요건과 상이한 제작 | F45: 재작업 | G45: MIP6 | H45: 현대건설 | I45: NCR-OOK-MR012-002 | J45: MR012 | K45: MR | L45: (M97-G-0767)_FIRE WATER PUMP | M45: Sulzer Pump | N45: Sulzer Pump KSA | O45: 45348 | P45: 45520 | Q45: 45471 | R45: As per Painting Procedure for Diesel Fire Water Pump(VD-MR012-015 Rev.1) and Coating Map M95-A-CE-021000, APCS 1A-External and APCS-2A Internalshall be applied for Diesel Day Tank But Int / Ext Paint applied in reverse
A46: 기계.설비 | B46: 일반기계_고정.회전 | C46: 미시공 | D46: 자재 | E46: 기타 | F46: 재작업 | G46: MIP6 | H46: 현대건설 | I46: NCR-OOK-MS018-001 | J46: MS018 | K46: MS | L46: Hot Oil Furnace PKG_Fuel gas skid | M46: ITT | N46: Sinergia | O46: 45462 | P46: 45595 | Q46: 45538 | R46: Final inspection including pneumatic test for all flanged joints shall be performed at the skid-mounted unit manufacturer’s facility to ensure that the unit meets requirements as described in the project specifications. However, the following activity couldn’t be completed during the final inspection due to the below: 1. The final visual inspection & Pneumatic test had been done partially because some valves (4pcs for each skid / Total 8 pcs) need to be delivered as loose supplied items due to the delay in production and shall be installed at site. (Missing Valve list) -. HV-040(8”/2ea), HV-057(1”/2ea), HV-061(1”/2ea), HV-063(2”/2ea) 2. Further FAT punch closing carried out on 24th May 2024 and noted partial punches were closed and remaining punches were noted in open condition. -. Open Punch items : No.7, 8, 17, 20, 27, 35, 37, 38, 40, and 41 In this regards, both ARAMCO and HDEC requested to deliver the skids to site urgently considering site construction schedule. The remaining punches shall be closed at site. Also, Vendor confirmed that there is no affect the functionality and warranty of overall package.
A47: 전기 | B47: 계기 | C47: 미시공 | D47: 자재 | E47: 기타 | F47: 재작업 | G47: MIP6 | H47: 현대건설 | I47: NCR-OOK-IN005-001 | J47: IN005 | K47: IN | L47: Pipeline Leak Detection System (PLDS) | M47: Emerson Korea | N47: - | O47: 45454 | P47: 45636 | Q47: 45593 | R47: During the FAT inspection of PLDS Server cabinet at Emerson Saudi Arabia Company, some FAT punch points were not rectified and closed. As per section 9.8 of SAEP-1151 requirement, contractor shall not release material with punch list items unless approval is obtained from company representative.
A48: 기계.설비 | B48: 일반기계_고정.회전 | C48: 기타 | D48: 자재 | E48: 도면, 기술시방서 요건과 상이한 제작 | F48: 폐기 | G48: MIP6 | H48: 현대건설 | I48: NCR-OOK-MS006-001 | J48: MS006 | K48: MS | L48: S&T Heat Exchanger | M48: ZAMIL PROCESS EQUIPMENT COMPANY (ZPEC) | N48: - | O48: 45509 | P48: 45554 | Q48: 45509 | R48: During M95-E-0202A&B (after PWHT) shell side hydrostatic test in stacked condition the glue marks near the gasket area were observed and the glue was used on the gasket on tag no M95-E-0202B. As per 32-SAMSS-007 para 10.2.17 the use of shellacs, glues, lead etc on gaskets during testing is prohobitted.
A49: 전기 | B49: 계기 | C49: 미시공 | D49: 자재 | E49: 기타 | F49: 재작업 | G49: MIP6 | H49: 현대건설 | I49: NCR-OOK-IN002-001 | J49: IN002 | K49: IN | L49: Analyzer System With Shelter | M49: ISG | N49: - | O49: 45523 | P49: 45596 | Q49: 45625 | R49: 1) The Installation of Sampling Conditioning system is not done along with its tubing work in M95-AH-002 Analyzer shelter and this is the fufilling ITP :VD-IN002-027 Sec:2.2.4 & 2.2.5.
A50: 기계.설비 | B50: 일반기계_고정.회전 | C50: 미시공 | D50: 자재 | E50: 기타 | F50: 폐기 | G50: MIP6 | H50: 현대건설 | I50: NCR-OOK-MS015-001 | J50: MS015 | K50: MS | L50: Vaccum Deaeration Package | M50: Veolia Water solutions | N50: - | O50: 45526 | P50: 45595 | Q50: 45603 | R50: he scale provided on the level gauge is showing measurement units in "mm" which is SI unit. As per 34-SAMSS-831 requirements, all measurement shall be done in English Units (which is inches or feets for level).
A51: 기계.설비 | B51: 일반기계_고정.회전 | C51: 자재불량 | D51: 자재 | E51: 품목의 결함, 손상 및 제작불량 | F51: 재작업 | G51: MIP6 | H51: 현대건설 | I51: NCR-OOK-MS008-003 | J51: MS008 | K51: MS | L51: Electrical Heater | M51: CHROMALOX | N51: - | O51: 45533 | P51: 45594 | Q51: 45595 | R51: It was observed that the TEE (TEE,BW,8"SCH80,SMLS,INC800H, 2PCS) which fabricated by IPP was identified as lnconel 800 I 330 stainless steel when evaluated via X-ray fluorescence (XRF) spectroscopy. In this case, the XRF identified the presence of silicon in the semi-quantitative results. When a ground portion of the TEE was evaluated via XRF, it identified the material as 'lnconel 800' / 330 stainless steel. TEE was observed to be in blasted condition upon inspection visit. The OD, ID, and Weld Prep areas are the affected areas noted to be blasted. Blast media was confirmed by IPP as it is Aluminum oxide with noted blast media residue on the ID of TEE in current condition. Weld prep areas noted to be blasted was found with rust contamination on and near weld prep areas
... A131: 기타 | B131: 기타 | C131: 기타 | D131: 기타. | E131: 기타 | F131: 현상태사용 | G131: SM12 | H131: 발주처 | I131: 500015424 | J131: RM001 | K131: RM | L131: Air Compressor Package | M131: Hanwha Power Systems | N131: Boldrocchi | O131: 44085 | P131: 44120 | Q131: 44110 | R131: During Sub-POs review for Instrument Air Compressor, Company has noticed that the Main manufacturer (HANWHA POWER SYSTEMS,ID#30006086) has placed their Sub PO (order# P20BD09002 dated Apr,20 2020) for the (Inlet Air Filter) with on-hold manufacturer (BOLDROCCHI, Italy ID# 30004546). Moreover, the Sub PO placed prior to obtain the Company review of the sub vendor list which is in violation to SAEP-1151, Para. 6.3 that stated "When requested, after P.O. award and prior to sub-P.O placements contractor shall submit sub-vendor list for company review that shall include as a minimum the following: material description, 9COM, approved sub-vendor (Name and ID), inspection level and material specification". In addition to the above, the Contractor did not Document/Report the Nonconformity as Contractor NCR (INCR) which is a violation to SchQ Para 7.5.2. Contractor is requested to provide Root Cause, Corrective action and Preventive action to eliminate reoccurrence of similar issues.
A132: 전기 | B132: 기타 | C132: 자재불량 | D132: 자재 | E132: 도면, 기술시방서 요건과 상이한 제작 | F132: 폐기 | G132: SM12 | H132: 발주처 | I132: 500017991 | J132: RM002 | K132: RM | L132: Motor for Centrifugal Pump, API 610 BB | M132: ITT Saudi Company | N132: TECO Middle East | O132: 44782 | P132: 44838 | Q132: 44813 | R132: NCR has been issued to document the repeated failure of stator sealed Winding conformance test for the Closed Loop Cooling Water Pump “T76-GM-0503A” manufactured by TECO middle east (MFR ID#30006593). The previously failed motor has been Re-tested on July, 3rd 2022 where the values of IR(Immersed in water condition after High Potential Test) was 10.7KΩ against the acceptance -criteria of 25MΩ per 17-SAMSS-502/6.3.4.4 and NEMA-MT1. The Manufacturer “TECO” failed to identify the proper RCA which caused a repeated failure for the same motor three times.
A133: 기계.설비 | B133: 기타 | C133: 기타 | D133: 자재 | E133: 도면, 기술시방서 요건과 상이한 제작 | F133: 재작업 | G133: SM12 | H133: 발주처 | I133: 500018751 | J133: PI002 | K133: PI | L133: PIPE (CS WELD) | M133: Hyundai Steel | N133: - | O133: 45006 | P133: 45103 | Q133: 45120 | R133: Hyundai Steel Company (HSC) ID#30008916 neither use pyrometers equipped heat treatment furnace nor attach thermocouples to the pipe which deviates from the heat treatment requirement in 01-SAMSS-043 para. 7.2. The thermocouples in HSC have been located on the upper side of the furnace wall which is not directly attached on the pipe. CONTRACTOR shall conduct full investigation, provide RCA and Corrective Actions to ensure meetings Company standards as well as ensuring the integrity of supplied materials. Contractor PO# 4600061069 IL# 107000205868 Material: CS WELD PIPE / ASTM A671 CC60 CL22. Quantities involved in violation: approximately 1,455 M out of 13,781 M
A134: 기계.설비 | B134: 일반기계_고정.회전 | C134: 자재불량 | D134: 자재 | E134: 도면, 기술시방서 요건과 상이한 제작 | F134: 재작업 | G134: SM12 | H134: 발주처 | I134: 500019612 | J134: MS010 | K134: MS | L134: Water Pump | M134: ZEECO MIDDLE EAST LTD | N134: GOULDS PUMPS | O134: 45266 | P134: 45340 | Q134: 45306 | R134: NCR has been issued to document the repeated failure of vibration test of the Water Pump “T74-G-0711A” for Flare Gas Recovery PKG manufactured by GOULDS PUMPS/Korea (MFR ID# 30006824). The high vibration issue has been initially observed on June, 2023 during the performance test where the Contractor documented the failure through INCR “NCR-OOK-MS010-002”. After implementing the corrective actions which include the replacement of 3rd stage impeller and other course of actions, the Pump has been Re-tested on Nov, 15 2023 where the high vibration issue was observed again which exceeded the acceptance tolerance (Max. 3.0 mm/sec) as per 31-SAMSS-004 Para 6.9.3 and API-610 table 8. The Manufacturer “GOULDS PUMPS” failed to identify the proper root causes which caused a repeated failure for the same Pump. # Measured vibration value during the initial testing (First Failure): DE _ Horizontal: 8.57 mm/sec / Vertical: 3.11 mm/sec NDE _ Horizontal: 10.17 mm/sec # Measured vibration value during the second Failure: DE – 6.002 mm/sec (Min. Continuous flow) / Vertical DE – 3.975 mm/sec (Mid. Flow) / Vertical Contractor Shall conduct full investigation, provide RCA and Corrective Actions to ensure the quality of supplied equipment. The ACD is Feb-18-2024.
A135: 기타 | B135: 기타 | C135: 기타 | D135: 기타. | E135: 기타 | F135: 현상태사용 | G135: SM12 | H135: 발주처 | I135: 500020202 | J135: RM014 | K135: RM | L135: Water Recovery Package | M135: VEOLIA WATER SOLUTIONS | N135: - | O135: 45518 | P135: 45523 | Q135: 45523 | R135: Description of Deficiency: Schedule Q Violation Hyundai violated the following: 1. Short notice for inspection (it was sent on Wednesday to conduct inspection on the next day), please find attached the notification. 2. Even though Hyundai received rejection for the notification, they proceed with the activities. 3. The inspection took place on Thursday and Friday (out working days). The inspection level is 3 and the material is chemical skid IL# 107000217826.
A136: 기타 | B136: 기타 | C136: 기타 | D136: 기타. | E136: 기타 | F136: 현상태사용 | G136: SM12 | H136: 발주처 | I136: 500020364 | J136: PI008 | K136: PI | L136: PTFE Lined Piping | M136: ELEMENTOS FLEXIBLES ARCONI SA | N136: - | O136: 45565 | P136: 45573 | Q136: 45573 | R136: CONTRACTOR have had an incompliance of SVL requirements. CONTRACTOR violated the following: 1. The SVL was submitted with incorrect material requested by the manufacturer. 2. Hyundai did not issue INCR for incorrect material requested in the SVL by the manufacturer. 3. Hyundai submitted the new SVL with the new material after receiving the materials 4. Hyundai did not implement the review comments on the SVL. [SM12] PI008 / PTFE Lined Piping IL107000223155
A137: 기계.설비 | B137: 일반기계_고정.회전 | C137: 기타 | D137: 기타. | E137: 기타 | F137: 현상태사용 | G137: STA4 | H137: 현대건설 | I137: STA4-MS003-ZAH-NCR-001 | K137: MS | L137: Pressure Vessel | O137: 45511 | P137: 45541 | Q137: 45534 | R137: Vendor placed order for dish head to “Arabian Oasis” prior to get approval from COMPANY. It is violation comparing to MR requirement
A138: 기계.설비 | B138: 기타 | C138: 기타 | D138: 자재 | E138: 도면, 기술시방서 요건과 상이한 제작 | F138: 재작업 | G138: STA4 | H138: 현대건설 | I138: STA4-PI003-HYS-NCR-001 | K138: PI | L138: CARBON STEEL SMLS PIPE | O138: 45541 | P138: 45547 | Q138: 45548 | R138: During marking inspection of pipe, the contract number displayed on the pipes is STA-PI-PO-003-4600066444, it is the same as the contract number shown on the cover of the contract. However, the contract number shown on all vendor documents and ITP is STA4-PI-PO-003-4600066444. The involved pipes refer to attachment-the item list of pipes involved PO number issue.
A139: 기계.설비 | B139: 기타 | C139: 기타 | D139: 자재 | E139: 도면, 기술시방서 요건과 상이한 제작 | F139: 폐기 | G139: STA4 | H139: 현대건설 | I139: STA4-PI004-PCK-NCR-001 | K139: PI | L139: CARBON STEEL WELDED PIPE | O139: 45590 | P139: 45651 | Q139: 45644 | R139: the welding control for production line of 508*9.52, founded incorrect weld wire (ESAB weld EH14) to be used in pipe with 508*9.52(pipe No: 12411266,12411272) due to WPS240610 by welder (Jin long, welder No: PW02208)
A140: 기계.설비 | B140: 일반기계_고정.회전 | C140: 기타 | D140: 설계 | E140: 설계, 도면의 부정확 | F140: 현상태사용 | G140: STA4 | H140: 현대건설 | I140: STA4-MS004-XIN-NCR-001 | K140: MS | L140: Filter | O140: 45744 | P140: 45807 | Q140: 45748 | R140: Longitudinal weld on Skirt and circumferential weld on Tag No. 404-S-3002 skirt were not identified weld number in the weld map (No. SA-AMI-000-4XIN-102005, Rev.0). The weld number for longitudinal weld of skirt of Tag No. 420-S-0008 (Seam No. A12) was not identified in the weld map (No. A-AMI-000-4XIN-102005, Rev.0.).
A141: 기계.설비 | B141: 일반기계_고정.회전 | C141: 기타 | D141: 시험.검사 | E141: 절차서, 지침서의 미준수 | F141: 재작업 | G141: STA4 | H141: 현대건설 | I141: STA4-MS016-STK-NCR-001 | K141: MS | L141: Deaerator | O141: 45686 | P141: 45746 | Q141: 45707 | R141: It was observed that the specimen of plates for SPWHT to meet AMIMS-D-3204 requirement are taken from longitudinal instead of Transvers to the rolling direction.
A142: 기계.설비 | B142: 일반기계_고정.회전 | C142: 기타 | D142: 설계 | E142: 기술검토 미비, 기술시방서의 부정확 | F142: 재작업 | G142: STA4 | H142: 현대건설 | I142: STA4-MS018-INX-NCR-001 | K142: MS | L142: LIN STORAGE & VAPORIZATION SYSTEM | O142: 45705 | P142: 45807 | Q142: 45783 | R142: The longitudinal welds of two adjacent shell rings offset kept by 30° instead of 60° on the following joints
A143: 기계.설비 | B143: 일반기계_고정.회전 | C143: 자재불량 | D143: 자재 | E143: 도면, 기술시방서 요건과 상이한 제작 | F143: 재작업 | G143: STA4 | H143: 현대건설 | I143: STA4-MR005-FLW-NCR-001 | K143: MR | L143: SALINE COOLING WATER PUMP (LOOP 1) 404-G-3001 A | O143: 45715 | P143: 45807 | Q143: 45737 | R143: 404-G-3001A, Saline Cooling Water Pump(LOOP 1). Flatness on pump pads is out of tolerance according to construction drawing and Flowserve procedure SQ 53 rev.2: required is 0.05 mm/mt while measured values are above 0.25 mm/mt.
A144: 전기 | B144: 급.배전설비 | C144: 기타 | D144: 시험.검사 | E144: 검사, 시험의 미시행 또는 미흡 | F144: 현상태사용 | G144: STA4 | H144: 현대건설 | I144: STA4-EL001-HIT-NCR-001 | K144: EL | L144: 230kv GIS Drives | O144: 45726 | P144: 45745 | Q144: 45747 | R144: According to SA-AMI-451-4HIT-402107_1, 230kV GIS: INSPECTION AND TEST PLAN-GIS, the highlighted inspection requires Contractor’s (HDEC) witness at Hitachi Energy Bulgaria. However, the Drives (Operating Mechanism for CB) were tested without Contractor’s (HDEC) witness and subsequently delivered to Hitachi Energy in KSA.
A145: 전기 | B145: 급.배전설비 | C145: 자재불량 | D145: 자재 | E145: 도면, 기술시방서 요건과 상이한 제작 | F145: 재작업 | G145: STA4 | H145: 현대건설 | I145: STA4-EL002-HYO-NCR-001 | K145: EL | L145: 230kv Power Transformer | O145: 45731 | P145: 45737 | Q145: 45737 | R145: During the Lightning Impulse Test on Phase H2 on 13th.Mar.2025, per SA-AMI-451-4HYO-402002_0_230kV Power TR - FACTORY INSPECTION & TEST PLAN, the result of sequence 7(LI 100%) was failed with the abnormal traces, when performed seventh full wave impulse on H2 terminal,
A146: 전기 | B146: 급.배전설비 | C146: 기타 | D146: 자재 | E146: 서류의 결함, 미비 | F146: 현상태사용 | G146: STA4 | H146: 현대건설 | I146: STA4-EL002-HYO-NCR-002 | K146: EL | L146: 230kv Power Transformer | O146: 45737 | P146: 45747 | Q146: 45747 | R146: According to SA-AMI-000-HDAI-510003_2 (Vendor Inspection Procedure), all punch list items must be cleared before the inspection release. Additionally, as per SA-AMI-451-HDAI-414002_0 (Unpriced Purchase Order for 230/34.5kV Power Transformer), delivery cannot proceed without the inspection release certificate (IRC) from the purchaser (HDEC). However, considering the site erection situation, HDEC has agreed to issue the IRC with outstanding punch list items (1ea / No .19), as noted in the NCR with the attached punch list. This NCR will be used to track the resolution of the punch list items and will be closed upon HDEC’s agreement.
A147: 전기 | B147: 기타 | C147: 손상 | D147: 시험.검사 | E147: 절차서, 지침서의 미준수 | F147: 폐기 | G147: STA4 | H147: 현대건설 | I147: STA4-MR001-HTC-ABB-NCR-001 | K147: MR | L147: Main Motor for Centrifugal Compressor (API617) | O147: 45743 | P147: 45948 | Q147: 45868 | R147: During the Final test of the motor, the forced oil lubrication system for the sleeve bearings was not activated, and the oil sumps were apparently dry. As a result, the bearings operated without proper lubrication, leading to excessive friction, heat generation, and severe damage to the bearing components and shaft journal. - Inspection Findings: Following the disassembly of the motor, the following damages were observed. However, please note that this is not the full information of the issues. A. DE and NDE bearing liners (white metal) completely destroyed B. Outer labyrinth seals (DE and NDE) damaged C. Inner labyrinth seals showed discoloration due to excessive heat D. Shaft journal damaged
A148: 전기 | B148: 기타 | C148: 기타 | D148: 자재 | E148: 서류의 결함, 미비 | F148: 현상태사용 | G148: STA4 | H148: 현대건설 | I148: STA4-MR005-FLW-NID-NCR-001 | K148: MR | L148: SOFT COOLING WATER PUMP DRIVING MOTORS | O148: 45743 | P148: 45972 | Q148: 45966 | R148: According to SA-AMI-000-HDAI-510003_2 (Vendor Inspection Procedure), all punch list items must be cleared before the inspection release. Additionally, as per SA-AMI-000-HDAI-412005_0 / UNPRICED PO FOR COOLING WATER PUMP (API 610 BB), delivery cannot proceed without the inspection release certificate (IRC) from the purchaser (HDEC). However, considering the characteristic of punch, HDEC has agreed to issue the IRC with 1 outstanding punch list item, as noted in the NCR with the attached punch list. This NCR will be used to track the resolution of the punch list items and will be closed upon HDEC’s agreement. - Note: The IECEx CES 25.0003X certification for the soft cooling pump (Type ET 1000) is nearing completion, with the hard copy expected soon. The draft copy currently shared confirms that this motor meets the certification requirements for hazardous area installations as specified by the project. Since the third-party certification body (CESI) is a government institution, the process of issuing the final copy is taking considerable time. The final copy will be verified during the review of the final dossier."
... A166: 기계.설비 | B166: 일반기계_고정.회전 | C166: 손상 | D166: 자재 | E166: 품목의 결함, 손상 및 제작불량 | F166: 수리 | G166: STA4 | H166: 현대건설 | I166: STA4-MS004-XIN-NCR-002 | K166: MS | L166: Filter | O166: 45897 | P166: 45930 | Q166: 45922 | R166: During the inspection stage, a dent was identified on the shell as per the below picture. The dent has dimensions of approximately 160 mm in length, 130 mm in width, and a maximum depth of 5 mm. This defect was found after the hydrostatic test and before the blasting operation.
A167: 기계.설비 | B167: 일반기계_고정.회전 | C167: 자재불량 | D167: 자재 | E167: 도면, 기술시방서 요건과 상이한 제작 | F167: 현상태사용 | G167: STA4 | H167: 현대건설 | I167: STA4-MR010-OPT-NCR-001 | K167: MR | L167: Spent Caustic Transfer Pump 420-G-0044-A/B | O167: 45898 | P167: 46112 | R167: Performance test was carried out as per STA4-MR010-OPT-IN-004 rev01, tag 420-G-0044-A, Spent Caustic Transfer Pump. After review performance test reports, it was found that power consumption was higher that required value.
A168: 전기 | B168: 제어설비 | C168: 미시공 | D168: 자재 | E168: 기타 | F168: 재작업 | G168: STA4 | H168: 현대건설 | I168: STA4-EL012-SEL2-NCR-001 | K168: EL | L168: PMS | O168: 45945 | P168: 46128 | Q168: 46065 | R168: With Company approval, a conditional IRC with NCR has been issued for the item described herein. Refer to the punch List_ STA4-EL-012-SEL-PMS-PL-001 (PMS) dated 05 OCT 2025. This NCR will be used to track the resolution of punch list item at site till final closure. (punch item #4)
A169: 기계.설비 | B169: 기타 | C169: 손상 | D169: 자재 | E169: 품목의 결함, 손상 및 제작불량 | F169: 재작업 | G169: STA4 | H169: 현대건설 | I169: STA4-PI016-AMP-NCR-001 | K169: PI | L169: VALVE; GATE; WEDGE; 26 INCH AND UP; FLANGED | O169: 45948 | P169: 45961 | Q169: 45992 | R169: Damages/ defects in RF detected. As general comment: roughness not uniform: 1) Isolated mechanical damages have been by grinding/ sand papering, resulting in a smooth/flat surface 2) Localized areas showing not uniform shape (to correspond with roughness 3,2-6,3 Ra)
A170: 기계.설비 | B170: 일반기계_고정.회전 | C170: 자재불량 | D170: 자재 | E170: 도면, 기술시방서 요건과 상이한 제작 | F170: 현상태사용 | G170: STA4 | H170: 현대건설 | I170: STA4-MS016-STK-NCR-004 | K170: MS | L170: Deaerator | O170: 45957 | P170: 46022 | Q170: 46014 | R170: During dimensional examination it was observed that N18 showed a deviation nozzle location 15mm where a tolerance of ±3 mm is allowed and deviation 1° from parallel plane where a tolerance of ±0.5° The stand-off of this nozzle is 600 mm. This nozzle will be used to install a pressure transmitter
A171: 전기 | B171: 제어설비 | C171: 미시공 | D171: 자재 | E171: 기타 | F171: 재작업 | G171: STA4 | H171: 현대건설 | I171: STA4-EL012-SEL2-NCR-002 | K171: EL | L171: PMS | O171: 45965 | P171: 46146 | Q171: 46087 | R171: With Company approval, a conditional IRC with NCR has been issued for the item described herein. Refer to the punch List_ STA4-EL-012-SEL-PMS-PL-001 (PMS) dated 05 OCT 2025. This NCR will be used to track the resolution of punch list item at site till final closure. (punch item #4)
A172: 기계.설비 | B172: 기타 | C172: 기타 | D172: 시험.검사 | E172: 점검, 및 시험자의 과실 | F172: 재작업 | G172: STA4 | H172: 현대건설 | I172: STA4-PI038-DON-NCR-001 | K172: PI | L172: Knife Gate Valve | O172: 45943 | P172: 45961 | Q172: 45960 | R172: During the pressure test, test pressure did not hold, due to leakages on test jig connections.
A173: 전기 | B173: 급.배전설비 | C173: 미시공 | D173: 자재 | E173: 기타 | F173: 재작업 | G173: STA4 | H173: 현대건설 | I173: STA4-EL008-AFN-NCR-001 | K173: EL | L173: LV SWGR | O173: 45952 | P173: 46132 | Q173: 46128 | R173: According to SA-AMI-000-HDAI-510003_2 (Vendor Inspection Procedure), all punch list items must be cleared before the inspection release. Additionally, as per the Sec. 5.9 of SA-AMI-000-HDAI-340707 (MATERIAL REQUISITION FOR LV SWGR) , Equipment/material shall not be released with punch list items unless approval is obtained from COMPANY Representative. However, considering the site erection situation and punch categories, HDEC has agreed to issue the IRC with outstanding punch list items as attached. This NCR will be used to track the resolution of the punch list items and will be closed upon HDEC’s agreement. 1. A 'partially closed sample & Partially Closed (SITE)' indicates that a full inspection and verification must be carried out upon installation at the site under supervision of ALFANAR. 2. Partially Closed (Documentation)’ refers to closure achieved through documentation updates All as-built documents must reflect the relevant punch items and obtain approval from our design team 3. As the IFAT punch items require SEL's involvement, they will be closed during the SAT stage All aforementioned site activity shall be supported by ALFANAR under get complete close. Attachment 1 : Final punch list - STA4-EL008-AF2-PL-001 (SSG) - STA4-EL008-AF2-PL-002 (SG,ESG) - STA4-EL008-AF2-PL-003 (IFAT with SEL) Attachment 2 : IRC (with condition) , STA4-EL008-AF2-IRC-001
A174: 전기 | B174: 급.배전설비 | C174: 미시공 | D174: 자재 | E174: 기타 | F174: 재작업 | G174: STA4 | H174: 현대건설 | I174: STA4-EL009-AFN-NCR-001 | K174: EL | L174: LV Controlgear | O174: 45963 | P174: 46143 | Q174: 46142 | R174: According to SA-AMI-000-HDAI-510003_2 (Vendor Inspection Procedure), all punch list items must be cleared before the inspection release. Additionally, as per SA-AMI-000-HDAI-340708, MATERIAL REQUISITION FOR LV Controlgear(MCC), equipment shall not be released with punch list items unless approval is obtained from COMPANY Representative. With Company approval considering the site urgency and punch categories, a conditional IRC with NCR has been issued for the item described herein. Please refer to the following three categories. 1. ”Partially Closed (SAMPLE)” indicates that a full inspection and verification must be carried out upon installation at the site under supervision of ALFANAR. 2. “Partially Closed (SITE)” indicates that a full inspection and verification must be carried out upon installation at the site under supervision of ALFANAR. 3. “Partially Closed (Documentation)”’ indicates that drawing and documentation must be updated as asbuilt. 4. As the IFAT punch items require SEL's involvement and SEL proposed to update and rectify them at site during the SAT stage This NCR will be used to track the resolution of the punch list items at site till final closure. Attachment; - Att.1 STA4-EL009-AF3-PL-001 FAT Punch list - Att.2 STA4-EL008-AF2-PL-003 IFAT Punch (Conducted together with LV SWGR)According to SA-AMI-000-HDAI-510003_2 (Vendor Inspection Procedure), all punch list items must be cleared before the inspection release. Additionally, as per SA-AMI-000-HDAI-340708, MATERIAL REQUISITION FOR LV Controlgear(MCC), equipment shall not be released with punch list items unless approval is obtained from COMPANY Representative. With Company approval considering the site urgency and punch categories, a conditional IRC with NCR has been issued for the item described herein. Please refer to the following three categories. 1. ”Partially Closed (SAMPLE)” indicates that a full inspection and verification must be carried out upon installation at the site under supervision of ALFANAR. 2. “Partially Closed (SITE)” indicates that a full inspection and verification must be carried out upon installation at the site under supervision of ALFANAR. 3. “Partially Closed (Documentation)”’ indicates that drawing and documentation must be updated as asbuilt. 4. As the IFAT punch items require SEL's involvement and SEL proposed to update and rectify them at site during the SAT stage This NCR will be used to track the resolution of the punch list items at site till final closure. Attachment; - Att.1 STA4-EL009-AF3-PL-001 FAT Punch list - Att.2 STA4-EL008-AF2-PL-003 IFAT Punch (Conducted together with LV SWGR)
A175: 기계.설비 | B175: 일반기계_고정.회전 | C175: 미시공 | D175: 자재 | E175: 기타 | F175: 재작업 | G175: STA4 | H175: 현대건설 | I175: STA4-MS017-SYC-NCR-001 | K175: MS | L175: Air Dryer Package (407-X-2001) | O175: 45968 | P175: 46142 | R175: Factory Acceptance Test (FAT) had been done at the skid-mounted unit manufacturer’s facility to ensure that the unit meets all functional and operational requirements as described in the project specifications. However, the following punch couldn’t be closed due to material issue. 1. Punch No. 38-2 from PL (STA4-MS017-SYC-PL-002) -. 4 leak points were founded (407-PG-05015, 05018, 05025, 05028 drain valve 1/2”) 2. Punch No. 15 from PL (STA4-MS017-SYC-PL-003) -. Twenty percent (20%) spare take off fittings and block valves shall be installed on the branch header and provided with low point drain valve. Currently, there were no drain valve and spare valves.
A176: 전기 | B176: 제어설비 | C176: 미시공 | D176: 자재 | E176: 기타 | F176: 재작업 | G176: STA4 | H176: 현대건설 | I176: STA4-EL012-SEL1-NCR-001 | K176: EL | L176: SS2, SS21, SS22 | O176: 45972 | P176: 46063 | Q176: 46090 | R176: With Company approval considering the site urgency and punch categories, a conditional IRC with NCR has been issued for open punch points as attached. This NCR will be used to track the resolution of the punch list items at site till final closure. Attachment; STA4-EL012-SEL1-PL-001 FAT Punch list
A177: 전기 | B177: 급.배전설비 | C177: 미시공 | D177: 자재 | E177: 기타 | F177: 재작업 | G177: STA4 | H177: 현대건설 | I177: STA4-EL007-AFN-NCR-001 | K177: EL | L177: HV Switchgear | O177: 46010 | P177: 46190 | R177: Description (with Nature of Non-Conformance / Attach sketch and Photograph if applicable) According to SA-AMI-000-HDAI-510003_2 (Vendor Inspection Procedure), all punch list items must be cleared before the inspection release. Additionally, as per the Sec. 5.9 of SA-AMI-000-HDAI-340706 (MATERIAL REQUISITION FOR HV SWGR) , Equipment/material shall not be released with punch list items unless approval is obtained from COMPANY Representative. However, considering the site erection situation and punch categories, HDEC has agreed to issue the IRC with outstanding punch list items as attached. This NCR will be used to track the resolution of the punch list items and will be closed upon HDEC’s agreement. 1. Partially Closed (SITE)' indicates that a full inspection and verification must be carried out upon installation at the site under supervision of ALFANAR. 2. Partially Closed (Documentation)’ indicates that document review for test report, certificate etc. Also, All as-built documents must reflect the relevant punch items and obtain approval from HDEC design team 3. CPY review’ It is under Company review, thus any necessary corrections will be implemented later on site. Based on the results of the CPY review, ALFANAR’s additional actions will be determined. All aforementioned site activity shall be supported by ALFANAR under get complete close. Attachment 1 : Final punch list - STA4-EL007-AF1-PL-001 (Open Punch) - STA4-EL007-AF1-PL-001 (Total) Attachment 2 : IRC (with condition) - STA4-EL007-AF1-IRC-001
A178: 기계.설비 | B178: 저장탱크 | C178: 기타 | D178: 자재 | E178: 도면, 기술시방서 요건과 상이한 제작 | F178: 수리 | G178: STA4 | H178: 현대건설 | I178: STA4-MS011-MHS-NCR-002 | K178: MS | L178: Shell plate | O178: 45972 | P178: 45991 | Q178: 46009 | R178: During surveillance on 11th Oct 2025, it was observed that the welder for part mark SP1-02A TK488 (405-T-0003) was welding over a pitted area without any approved procedure or prior approval. Dwg Ref: SA-AMl-405-4MHS-101037 Sheet 03 of 06 Rev.02 & Refer attached Annexure-1
A179: 기계.설비 | B179: 저장탱크 | C179: 기타 | D179: 시험.검사 | E179: 검사, 시험의 미시행 또는 미흡 | F179: 재작업 | G179: STA4 | H179: 현대건설 | I179: STA4-MS011-MHS-NCR-003 | K179: MS | L179: Aluminum dome roof | O179: 46009 | P179: 46096 | Q179: 46085 | R179: For the aluminum dome roof (Inspection Level-3), the material was dispatched to site without prior submission and approval of the applicable ITP and required inspection documents, which is non-compliant with the project quality requirements.
A180: 기계.설비 | B180: 일반기계_고정.회전 | C180: 자재불량 | D180: 자재 | E180: 도면, 기술시방서 요건과 상이한 제작 | F180: 현상태사용 | G180: STA4 | H180: 현대건설 | I180: STA4-MR010-OPT-NCR-002 | K180: MR | L180: Spent Caustic Transfer Pump 420-G-0044-A/B | O180: 45995 | P180: 46142 | R180: For high power consumption, waiver request was submitted for CPY approval. CTR would like to deliver sealless pumps to site conditionally with this open punch.
A181: 전기 | B181: 제어설비 | C181: 자재불량 | D181: 자재 | E181: 도면, 기술시방서 요건과 상이한 제작 | F181: 현상태사용 | G181: STA4 | H181: 현대건설 | I181: STA4-CI001-EME-NCR-001 | K181: CI | L181: PDC(Power Dst.) | O181: 46042 | P181: 46222 | R181: According to SA-AMI-000-HDAI-510003_2 (Vendor Inspection Procedure), all punch list items must be cleared before the inspection release. Additionally, as per SA-AMI-000-HDAI-353101, MATERIAL REQUISITION FOR PCS equipment shall not be released with punch list items unless approval is obtained from COMPANY Representative. A conditional IRC has been issued for the 7(seven) open punch items which require to be as built. Drawing update can be finalized at the time of final shipment of the rest batches.
A182: 기계.설비 | B182: 일반기계_고정.회전 | C182: 자재불량 | D182: 자재 | E182: 서류의 결함, 미비 | F182: 현상태사용 | G182: STA4 | H182: 현대건설 | I182: STA4-MS020-ZE1-MO-NCR-001 | K182: MS | L182: Incinerator Chamber & Stack | O182: 46036 | P182: 46124 | Q182: 46051 | R182: Before issuance IRC, pending drawing which are not approved by CPY were found. These drawings were approved by CTR only. CTR would like to deliver incinerator chamber & stack to site conditionally with this open punch.
A183: 기계.설비 | B183: 일반기계_고정.회전 | C183: 자재불량 | D183: 자재 | E183: 도면, 기술시방서 요건과 상이한 제작 | F183: 현상태사용 | G183: STA4 | H183: 현대건설 | I183: STA4-MS016-STK-NCR-005 | K183: MS | L183: Saddle of Deaerator | O183: 46044 | P183: 46134 | Q183: 46081 | R183: During final painting inspection, inspector found non-conformance final coating color for saddle between approved procedure (RAL 7042) and actual (RAL 7032).
A184: 기계.설비 | B184: 일반기계_고정.회전 | C184: 자재불량 | D184: 자재 | E184: 도면, 기술시방서 요건과 상이한 제작 | F184: 재작업 | G184: STA4 | H184: 현대건설 | I184: STA4-MS023-KES-SMF-NCR-001 | K184: MS | L184: Separator vessel for flare gas recovery package (430-D-0102) | O184: 46072 | P184: 46142 | Q184: 46133 | R184: During the Final Visual and Dimensional Inspection (FVDI) of the Separator Vessel, Equipment Tag No. 430-D-0102, carried out in accordance with the approved ITP Stage No. 20, both the internal and external areas of the vessel were inspected. It was observed that the external dish head nozzles, Item Nos. L3A, L3B, L5A, and L5B, do not conform to the requirements specified in the approved detailed fabrication drawing No. SA-AMI-430-4KES-101007_F. As per the approved drawing, the required dimension from the dish center to each nozzle is 610 mm. But the actual measured dimension is 605 mm, resulting in a deviation of 5 mm. This deviation exceeds the specified tolerance and requires root cause and corrective action.
A185: 전기 | B185: 제어설비 | C185: 미시공 | D185: 자재 | E185: 기타 | F185: 재작업 | G185: STA4 | H185: 현대건설 | I185: STA4-EL012-SEL1-NCR-002 | K185: EL | L185: SS2, SS21, SS22 | O185: 46107 | P185: 46197 | R185: With Company approval considering the site urgency and punch categories, a conditional IRC with NCR has been issued for open punch points as attached. This NCR will be used to track the resolution of the punch list items at site till final closure. Attachment; STA4-EL012-SEL1-PL-002 FAT Punch list
A186: 전기 | B186: 계장제어 | C186: 자재불량 | D186: 자재 | E186: 도면, 기술시방서 요건과 상이한 제작 | F186: 현상태사용 | G186: STA4 | H186: 현대건설 | I186: STA4-CI001-EME-NCR-002 | K186: CI | L186: PCS overall | O186: 46087 | P186: 46178 | R186: According to SA-AMI-000-HDAI-510003_2 (Vendor Inspection Procedure), all punch list items must be cleared before the_x000D_inspection release. Additionally, as per SA-AMI-000-HDAI-353101, MATERIAL REQUISITION FOR PCS equipment shall not_x000D_be released with punch list items unless approval is obtained from COMPANY Representative. This NCR is issued based on the punch list items identified during the Final Wrap-Up Meeting held on February 9. 2026_x000D_All punch items will be managed through Test Studio (Emerson’s system) A final wrap-up will be again conducted at the time of SAT completion, and any remaining follow-up items will be transferred to_x000D_ICAPS for further tracking and closure.
A187: 기계.설비 | B187: 기타 | C187: 기타 | D187: 시험.검사 | E187: 검사, 시험의 미시행 또는 미흡 | F187: 기타 | G187: STA4 | H187: 현대건설 | I187: STA4-CI005-VAL-NCR-002 | K187: CI | L187: On-Off Valve (Ball) | O187: 46120 | P187: 46173 | R187: According to the TBE and the valve datasheet (instrument specification sheets), the standard code for all Trunnion Ball Valves shall be API 6D. However, the vendor has not inspected the valves in accordance with API 6D. Eleven of these valves require re-testing because the high-pressure seat test / DBB test was omitted. Total Q’ty: Trunnion Type Ball Valve (27 pcs)
A188: 기타 | B188: 기타 | C188: 기타 | D188: 기타. | E188: 기타 | F188: 현상태사용 | G188: STA4 | H188: 발주처 | I188: AMIRAL-P4-NCR-0376 | K188: 공통 | O188: 46035 | P188: 46125 | Q188: 46110 | R188: CTR-INCR for Procurement (STA4-NCR-OOK-QM-006) is escalated to company (AMIRAL) NCR, for not completing the proposed corrective action (CA) within the specified ECD (in line with "NON-CONFORMANCE MANAGEMENT PROCEDURE" (SA-AMl-OOO-EQAC-000003) STA4-NCR-OOK-QM-006: It is observed that 257 VENDOR documents have not been submitted for over 45 days since they were received from the company. This is clear violation of SA-AMI-OOO-HDAI-110002, para 5.9.1. Delayed document submission will have a considerable impact in the manufacturing, inspection and testing activities at vendor shops and subsequent delivery impact. Contractor to comply with the requirements and implement both corrective and preventive measures. A root cause analysis should also be conducted to prevent the recurrence of such non-compliance in future projects.
A189: 전기 | B189: 기타 | C189: 기타 | D189: 설계 | E189: 기술검토 미비, 기술시방서의 부정확 | F189: 현상태사용 | G189: STA4 | H189: 발주처 | I189: AMIRAL-P4-NCR-0391 | K189: CI | O189: 46058 | P189: 46147 | R189: This Company NCR is issued to Contractor HYUNDAI (PKG-4) for Fiber Optic (F.O.) cables for_x000D_the AMIRAL Project supplied by the approved vendor MIDDLE EAST FIBER CABLE_x000D_MANUFACTURING COMPANY (MEFC), due to failure to comply with the contractual and_x000D_technical requirements of AMIMS-J-4913, Clause 6.1.3, and AMIITP-J-347600 which mandates_x000D_the Oil-resistant test for F.O. cables. MEFC is obligated to conduct the Oil-resistant test on the_x000D_final F.O. cable and invite Company for test witnessing (Inspection Level 2), and provide a valid,_x000D_project-specific test certificate. However, to date, Contractor/MEFC failed to perform the required_x000D_oil test and has only submitted an outdated certificate from a sub-supplier (SHAKUN Polymers)_x000D_applicable solely to sheath material, which is not acceptable and does not demonstrate_x000D_compliance with AMIRAL requirements. The Contractor/Vendor is therefore required to_x000D_immediately conduct the oil test in accordance with the applicable specifications and approved_x000D_waivers, arrange Company witnessing. Contractor Hyundai, through the Project Management_x000D_Team (PMT), is hereby instructed to investigate and determine the root cause of this_x000D_nonconformity and to develop, submit, and implement effective corrective and preventive_x000D_actions.
A190: 기타 | B190: 기타 | C190: 기타 | D190: 기타. | E190: 기타 | F190: 현상태사용 | G190: SAC2 | H190: 현대건설 | I190: NCR-OOK-PI-0001 | K190: PI | O190: 45597 | P190: 45639 | Q190: 45610 | R190: Contractor found that piping PO for Flange-3 from ULMA under MR No. JUS&ICS2-PI-MR-0031 has singed on July 2, 2024 before obtaining the No Objection Letter from Company as approval was given in July 8, 2024.
A191: 기타 | B191: 기타 | C191: 기타 | D191: 기타. | E191: 기타 | F191: 현상태사용 | G191: SAC2 | H191: 현대건설 | I191: NCR-OOK-PI-0002 | K191: PI | O191: 45650 | P191: 45695 | Q191: 45701 | R191: Contractor found that 'Change Order(P.O Addendum)' for Piping Materials were submitted to company later than the Contractural Due date (10 Working days)
A192: 기타 | B192: 기타 | C192: 기타 | D192: 기타. | E192: 기타 | F192: 현상태사용 | G192: SAC2 | H192: 현대건설 | I192: NCR-OOK-PI-0003 | K192: PI | O192: 45663 | P192: 45681 | Q192: 45681 | R192: Regarding the process of bid equalization for pipe support, IK Manufacturer obtained confidential bid equalization documents which the information should not be shared with the bidders.
A193: 기타 | B193: 기타 | C193: 기타 | D193: 기타. | E193: 기타 | F193: 현상태사용 | G193: SAC2 | H193: 현대건설 | I193: NCR-OOK-CI-0001 | K193: CI | O193: 45665 | P193: 45730 | Q193: 45729 | R193: Contractor found that Instrumentation PO Addendum No.1 was issued without Technical Bid Evalluation revision. 1. Item : Control Valve (General & Non-General) 2. Original PO No. : JUS&ICS2-CI-PO-0015 & 0016 (Signed on 5th Sep, 2024) 3. PO Addendum No.1 Issue Date : 12th Dec, 2024 (for Oxygen service) 4. Technical Bid Evalluation No. : JUS&ICS2-CI-TBE-0015 & 0016 (Issued on 12th Nov, 2024) 5. TBE Rev.00 was issued with the ARAMCO's comments on the Oxygen Valve still pending resolution
A194: 기계.설비 | B194: 기타 | C194: 자재불량 | D194: 자재 | E194: 도면, 기술시방서 요건과 상이한 제작 | F194: 현상태사용 | G194: SAC2 | H194: 현대건설 | I194: JUS&ICS2-PI-PO-0022-1-NCR-001 | K194: PI | O194: 45674 | P194: 45747 | Q194: 45701 | R194: Contractor found that The raw material used to Manufacture the wrought fitting exceeded the sulfur content limit specified in the project requirements. 1. Vendor Name : ERNE Fitting (MFR # 30005383) 2. Violation Details for Sulfur Contents (%) * Requirement in 02-SAMSS-005 : Shall not exceed 0.003% * Actual Contents in MTC : Below table
A195: 기타 | B195: 기타 | C195: 기타 | D195: 기타. | E195: 기타 | F195: 재작업 | G195: SAC2 | H195: 현대건설 | I195: JUS&ICS2-CI-PO-0007-NCR-001 | K195: CI | O195: 45904 | P195: 45993 | Q195: 45973 | R195: Tag no. : 861-B-6106, 862-B-6206A, 869-400-B-6906, 869-500-B-6906 (Analyzer Shelter) It was submitted that In-Process inspection would be carried out at an unapproved location. 1. Notified location : No. 282, Qingwei Road, Qingcun Town, Fengxian District, Shanghai (Shanghai Qianyi Industrial Co., Ltd) 2. Approved location : No. 4528, Kangxin Road, Shanghai (ABB ENGINEERING (SHANGHAI) LTD - MFR no_30005668)
A196: 기계.설비 | B196: 기타 | C196: 기타 | D196: 자재 | E196: 도면, 기술시방서 요건과 상이한 제작 | F196: 수리 | G196: SAC2 | H196: 현대건설 | I196: JUS&ICS2-PI-PO-0007-NCR-001 | K196: PI | O196: 45925 | P196: 46014 | Q196: 46006 | R196: IL No. : 107000292139, Cladtek Arabia KSA, Item: Clad Piping, Item No.: Line Item No. 390 (Ident Code: M361761213 / Vendor Internal Code : CA98-WO-039-00004 ), Item Description: CS API-5L-BM-PSL2 SAWL w/100% RT BE B36.10M N06625 CLADDING Sour 68 inch, 1.125". During witnessing of repair welding after CRA at Cladtek, using Approved WPS CA098-WPS-001I, the following observations/non-conformities were noted: 1. Discrepancy with the WPS (1) Welding Position (QW-405): The WPS specifies that repair welding shall be performed in the flat (1G) position by rotating the pipe. However, the welder performed welding in a fixed 5G position, carrying out repairs from inside the pipe in multiple orientations (overhead, vertical, and horizontal). (2) Amperage Range (QW-409): The WPS specifies a maximum of 140 Amps, whereas the welder used 151 Amps. 2. CRA Weld Defects: On the same pipe (CA98-WO-039-00004), after completion of CRA welding, several unusual visual defects/Pin holes and uncladded areas were observed (see the attached images).
A197: 기타 | B197: 기타 | C197: 기타 | D197: 기타. | E197: 기타 | F197: 현상태사용 | G197: SAC2 | H197: 발주처 | I197: 500021221 | K197: CI | O197: 45916 | P197: 46006 | Q197: 46002 | R197: It has been identified that instrument cable tray clamps supplied by ABAHSAIN COPE (ID 30005833) under PO JUS-ICS2-CI-PO-0042 do not comply with the approved project specifications, NEMA VE 1 and 2, and design drawings (VD-CI0042-102 Rev. C). The clamps were suppl ied with a welded construction, whereas a one-piece design was specified. In addition, Contractor did not provide cable tray’s inst a llation and erection instruction by manufacturer which is key deliverable part of NMR-603. The contractor failed to report these d is crepancies through INCRs and accepted the release of material despite non-conformities, which violates Schedule Q para. 7.5.3, S A E P-1151 10.2, and the contractor’s Quality Plan 8.7.3 (JUS-ICS2-PM-PD-6001 Rev.00). As per SAEP-381 5.2, these are classified a s a m oderate violations and therefore Company NCR has been issued to investigate the root causes and implement corrective actions t o prev ent recurrence.
A198: 기계.설비 | B198: 일반기계_고정.회전 | C198: 자재불량 | D198: 자재 | E198: 도면, 기술시방서 요건과 상이한 제작 | F198: 재작업 | G198: SHN1 | H198: 현대건설 | I198: SHN1-2110-2001-002-KHA-NCR-0001 | J198: MS-2110-2001-002 | K198: MS | L198: Radiant Module (Steel structure) | M198: JNK Heaters | N198: KHAN Plant (KIC) | O198: 45250 | P198: 45351 | Q198: 45384 | R198: It’s observed that painting color for steel structure is wrongly applied with Blue gray instead of gray (Munsell No. N-6) and mosf of them have been installed for back to back module (H-211103 & 04) at KHAN Plant
A199: 기계.설비 | B199: 일반기계_고정.회전 | C199: 자재불량 | D199: 자재 | E199: 도면, 기술시방서 요건과 상이한 제작 | F199: 현상태사용 | G199: SHN1 | H199: 현대건설 | I199: SHN1-2110-2001-001-ARV-NCR-0001 | J199: MS-2110-2001-001 | K199: MS | L199: Transfer Line Exchanger | M199: Lummus | N199: Arvos | O199: 45261 | P199: 45351 | Q199: 45386 | R199: During inspection before PWHT, the dimension “F” as per dimensional check found out of tolearance by 2mm
A200: 기계.설비 | B200: 일반기계_고정.회전 | C200: 자재불량 | D200: 자재 | E200: 도면, 기술시방서 요건과 상이한 제작 | F200: 폐기 | G200: SHN1 | H200: 현대건설 | I200: SHN1-2110-2001-001-ENG-NCR-0001 | J200: MS-2110-2001-001 | K200: MS | L200: Radiant Coil (Gas Heater) | M200: Lummus | N200: Engemasa | O200: 45280 | P200: 45356 | Q200: 45358 | R200: It was found that items 222014 and 222015, SMLs Pipe OD 60.3 x 3.9 x 604 & 814 mm, were thicker than specified, revealing to be schedule 80 instead of schedule 40 as requested on material list of S-Oil Shaheen Project. 222014 (ASTM A312 TP347H) : 204 pcs - 192 + 12 (spares) pcs 222015 (ASTM A312 TP347H) : 204 pcs - 192 + 12 (spares) pcs
A201: 기계.설비 | B201: 일반기계_고정.회전 | C201: 기타 | D201: 자재 | E201: 도면, 기술시방서 요건과 상이한 제작 | F201: 재작업 | G201: SHN1 | H201: 현대건설 | I201: SHN1-2110-2001-002-IPL-NCR-0001 | J201: MS-2110-2001-002 | K201: MS | L201: Convection Module & GTE Duct | M201: JNK Heaters | N201: I-Plant | O201: 45299 | P201: 45351 | Q201: 45421 | R201: It’s observed that Intermediate heat treatment have not been applied on weld joint between manifold pipe (SA335 P91) to weldolet (SA335 F91) as per ASME SEC.I PW 38.8 - Item : H211101 ~ H211104 / USSH Outlet Pipe
A202: 기계.설비 | B202: 일반기계_고정.회전 | C202: 자재불량 | D202: 설계 | E202: 설계, 도면의 부정확 | F202: 재작업 | G202: SHN1 | H202: 현대건설 | I202: SHN1-2110-2001-002-IPL-NCR-0002 | J202: MS-2110-2001-002 | K202: MS | L202: Convection Module & GTE Duct | M202: JNK Heaters | N202: I-Plant | O202: 45366 | P202: 45455 | Q202: 45443 | R202: During material receiving inspection and pre-assembly, it’s observed that the strainer on cross over can’t be assembled because thickness of intermediate wall on concentric reducer (Item No. 123506 & 223506 / O.D 273.1 x 15.08 & O.D 219.1 x 8.18) where strainer support (Item No. 123508 & 223508) to be inserted is thick and various. - Reducer - Q’ty : 80 ea (8 x 10 Heaters) / Heat No. : I69722 - Strainer - Q’ty : 80 ea (8 x 10 Heaters) / Heat No. : E71K
A203: 기계.설비 | B203: 일반기계_고정.회전 | C203: 기타 | D203: 시험.검사 | E203: 절차서, 지침서의 미준수 | F203: 현상태사용 | G203: SHN1 | H203: 현대건설 | I203: SHN1-2110-2001-002-KHA-NCR-0002 | J203: MS-2110-2001-002 | K203: MS | L203: Radiant Module | M203: JNK Heaters | N203: KHAN Plant | O203: 45373 | P203: 45464 | Q203: 45378 | R203: During document review on refractory lining (castable) for peep door for H-211104, it’s observed that water and casing temperature were lower than spec. requirement (SHAHEEN-COM-ML-SPC-0010 Para. 5.3.10) as following;
A204: 기계.설비 | B204: 일반기계_고정.회전 | C204: 균열 | D204: 자재 | E204: 품목의 결함, 손상 및 제작불량 | F204: 재작업 | G204: SHN1 | H204: 현대건설 | I204: SHN1-2110-2001-002-IPL-NCR-0003 | J204: MS-2110-2001-002 | K204: MS | L204: Convection Module & GTE Duct | M204: JNK Heaters | N204: I-Plant | O204: 45435 | P204: 45653 | Q204: 45617 | R204: During material receiving inspection and pre-assembly for convection module (CM-01 for 8 Liquid Heaters), it’s observed that 1. the clearance between ITS (Part No. 131002) and support guide is not designed so that it can’t be assembled 2. the clearance between ITS (Part No. 131002) and support bracket (Part No. 123006) spacing between was designed with 1mm gap. In addition, the cast support brackets were fabricated smaller than the drawing so that ITS can’t be installed. For the detail, please find attached investigation reports describing measuring result.
A205: 기계.설비 | B205: 일반기계_고정.회전 | C205: 기타 | D205: 자재 | E205: 도면, 기술시방서 요건과 상이한 제작 | F205: 재작업 | G205: SHN1 | H205: 현대건설 | I205: SHN1-2110-2001-002-IPL-NCR-0004 | J205: MS-2110-2001-002 | K205: MS | L205: Convection Module & GTE Duct | M205: JNK Heaters | N205: I-Plant | O205: 45435 | P205: 45653 | Q205: 45650 | R205: During material receiving inspection and pre-assembly for convection module (CM-01 for 8 Liquid Heaters), it’s observed that Interference between upper ITS (Part No. 131002) and lower ITS (Part No. 131001) is made against design value with 11mm, because the supplied ITS is thicker than drawing, also surface condition is irregular and bent outward. For the detail, please find attached investigation reports describing measuring result.
A206: 기타 | B206: 기타 | C206: 기타 | D206: 자재 | E206: 미승인 자재 사용 | F206: 현상태사용 | G206: SHN1 | H206: 현대건설 | I206: SHN1-2110-2001-001-JZH-NCR-0001 | J206: MS-2110-2001-001 | K206: MS | L206: Burners | M206: Lummus | N206: John Zink | O206: 45495 | P206: 45618 | Q206: 45618 | R206: During receiving inspection, it was found that two(2ea) burners for H-211107 are wrongly fabricated and delivered. 1) External : Lighting port/Pilot/Sight port locations are rotated about 45 degree from the drawing. 2) Internal : Turning vane angle is rotated about 45 degree from the drawing.
...

Sheet PQAN
A1: 순번 | B1: PQAN No. | C1: PQAN 배포일자 | D1: 연 | E1: 월 | F1: Feedback | G1: 검토자 | H1: 공종 | I1: PO No. | J1: NCR No. | K1: Transmittal No. | L1: 제목 | M1: 품목 | N1: 공급업체 | O1: 국가 | P1: 지역 | Q1: 발견 시기 | R1: 발견 장소 | S1: 개요 | T1: 원인 | U1: 후속/예방 조치 (권고) | V1: 이미지 URL (Teams)
A2: =ROW()-1 -> 1 | B2: PQAN-2025-001 | C2: 45727 | D2: 2025 | E2: 3 | F2: 0 | G2: 유요석 | H2: 배관 | I2: PI016 | J2: - | K2: - | L2: 대구경 Lateral Tee 수압 시험 후 변형 | M2: Fabricated Lateral Tee | N2: GAS METAL TECH | O2: 사우디아라비아 | P2: DAMMAM | Q2: Hydrostatic Test | R2: Vendor | S2: 대구경 Lateral Tee (84” x 80”, 68” x 54”, 48” x 30” 등)에 대한 수압 시험 후 Heel Side Notch 부분 변형 (Bulging) 발생 | T2: Header – Branch 연결부에 국부적인 과부하 (압력) 발생 (타 구역 대비 수압시험 압력 ↑) 사업주 요건에 따른 수압시험 압력 계산식은 실제 재료의 강도 검증 목적으로 (실제 재료 두께 적용)_x000B_90% SMYS (Specified Material Yield Strength)을 고려한 Barlow’s Formula를 적용하기 때문에_x000B_계산된 수압시험 압력이 일반적인 계산 방식 (ASME B31.3 / 설계 압력 & 온도에 따른 두께 적용) 대비 높음 | V2: https://teams.microsoft.com/l/message/19:KlEVjYWGS-QmxCKqE5H4Ofn-AvSWTK6hz_ErP7aUdvg1@thread.tacv2/1770610954279?tenantId=5fcb0def-a698-40ce-a73a-ea61130c13c6&groupId=80bfa3ae-81fa-4e4e-ba65-7b9c876b82d8&parentMessageId=1770610954279&teamName=P-Quality%20Alert%20Notice%20(PQAN)&channelName=PQAN%20Library&createdTime=1770610954279
A3: =ROW()-1 -> 2 | B3: PQAN-2025-002 | C3: 45765 | D3: 2025 | E3: 4 | F3: 0 | G3: 유요석 | H3: 회전 | I3: MR001 | J3: NCR-STA4-MR001-HTC-ABB-001 | K3: - | L3: Centrifugal Compressor의 Main Motor FAT 중 Trip 발생 | M3: Main Motor for Centrifugal Compressor | N3: ABB Finland | O3: 핀란드 | P3: HELSINKI | Q3: Factory Acceptance Test | R3: Sub-Vendor | S3: Motor FAT (Routine & Type Test)를 위한 기동 후 Rated Speed에서 고 진동 및 급격한 Voltage 저하 발생하였고 Load Generator에 의해 Motor 가동 중지됨. 분해 점검 결과, Rotor / Bearing / Labyrinth Seal 손상 확인되어 납기 지연 (재 제작) 발생 | T3: 해당 Motor는 Forced Lubrication System을 통해 Lube Oil이 공급되는 Type으로 Motor 기동 시 Oil Pump 가동이 우선 요구되나 Vendor 시험 운전원의 실수로 Oil Pump 미 가동 상태에서 Motor 기동하였음 (FAT 절차 미준수) | V3: https://teams.microsoft.com/l/message/19:KlEVjYWGS-QmxCKqE5H4Ofn-AvSWTK6hz_ErP7aUdvg1@thread.tacv2/1770611042032?tenantId=5fcb0def-a698-40ce-a73a-ea61130c13c6&groupId=80bfa3ae-81fa-4e4e-ba65-7b9c876b82d8&parentMessageId=1770611042032&teamName=P-Quality%20Alert%20Notice%20(PQAN)&channelName=PQAN%20Library&createdTime=1770611042032
A4: =ROW()-1 -> 3 | B4: PQAN-2025-003 | C4: 45799 | D4: 2025 | E4: 5 | F4: 0 | G4: 유요석 | H4: 장치 | L4: Refractory Lining 균열 | M4: Refractory Lining (Castable) in Fired Equipment | N4: 아이플랜트 | O4: 대한민국 | Q4: Final Inspection | R4: Vendor | S4: Fired Heater의 Refractory Lining (Castable) 시공 & Pre-Dry out 후 균열 발생 Incinerator의 현장 설치 후 내부 확인 시 균열 발견 | T4: 제작 ① 내화물의 배합 조건 (대기 / 물 / Mixing 온도, Dry Mixing, 배합 비율 등) 미 준수 ② 내화물 시공 후 잔존 수분 제거 시 (Pre-Dry out) 열팽창/수축 (Heating/Cooling Rate) 관리 미흡 ③ 내화물 작업 후 Full Curing 전, 후속작업을 위한 Lifting에 따른 충격과 Pre-Dry out 시 Castable 타설 부위의 국부하중-처짐 (임시 지지대 수량 및 위치) 관리 미흡 운송 및 설치 (시간이 지남에 따라 미세 균열이 Crack으로 성장) ① 운송 과정의 진동과 하역 시 발생하는 충격, 설치과정에서의 미세한 뒤틀림 (구조적 응력) | V4: https://teams.microsoft.com/l/message/19:KlEVjYWGS-QmxCKqE5H4Ofn-AvSWTK6hz_ErP7aUdvg1@thread.tacv2/1770611127739?tenantId=5fcb0def-a698-40ce-a73a-ea61130c13c6&groupId=80bfa3ae-81fa-4e4e-ba65-7b9c876b82d8&parentMessageId=1770611127739&teamName=P-Quality%20Alert%20Notice%20(PQAN)&channelName=PQAN%20Library&createdTime=1770611127739
A5: =ROW()-1 -> 4 | B5: PQAN-2025-004 | C5: 45835 | D5: 2025 | E5: 6 | F5: 0 | G5: 유요석 | H5: 배관 | L5: Coating film 균열/박리 (Cracking/Flaking) | M5: Seal Drum & PTFE Lining Piping spools | N5: Arconi / Misa | O5: 스페인 / 사우디아라비아 | Q5: After delivery (Site) | R5: Site | S5: Seal Drum 현장 설치 후 Internal Painting의 Flaking 발견됨 PTFE Lined Piping 현장 설치 후 External Painting의 Flaking 발생함 | T5: Surface preparation 불량 ① 기기 Internal 설치 상태에서 (탈착 불가) 도장 작업 수행으로, 표면 처리 (Surface preparation) 위한 Access 확보 애로 (표면 조도 불량) ② 도장작업 前, 표면 cleaning 작업 미흡 (이물질 잔존) Painting Control 미흡 ① Excessive coating film 적용에 따른 도막 Internal stress 증가  크랙 유발 ② 도장 작업 관리 부족 (전체 Spool Inspection Report에 표면처리, 1st, 2nd, 3rd Coat 치수 동일) | V5: https://teams.microsoft.com/l/message/19:KlEVjYWGS-QmxCKqE5H4Ofn-AvSWTK6hz_ErP7aUdvg1@thread.tacv2/1770611363619?tenantId=5fcb0def-a698-40ce-a73a-ea61130c13c6&groupId=80bfa3ae-81fa-4e4e-ba65-7b9c876b82d8&parentMessageId=1770611363619&teamName=P-Quality%20Alert%20Notice%20(PQAN)&channelName=PQAN%20Library&createdTime=1770611363619
A6: =ROW()-1 -> 5 | B6: PQAN-2025-005 | C6: 45868 | D6: 2025 | E6: 7 | F6: 0 | G6: 유요석 | H6: 장치 | L6: Cracking Heater용 Burner 제작/조립 불량 | M6: Hearth Burner (Cracking Heater) | N6: John Zink | O6: 미국 | P6: TULSA | Q6: After delivery (Site) | R6: Site | S6: Hearth Burner 내부 S/S Liner Plate 마감 불량으로 Gap 발생 및 내부 보온재 돌출 Hearth Burner와 Burner Tile 조립 시 Burner 상단의 Primary Riser Tip 과 Tile Hole의 Alignment가 허용 공차 (±3mm) 벗어남 | T6: - By Vendor ① 작업자 기량 & 제작 관리 수준 미흡 (균일 하지 않은 제품 품질) : 현장 입고된 480개 Hearth Burner 중 436개 불량판정 & 수리, Primary Riser Tip 1440ea (버너당 3개) 중 297개 불량 & 재 제작 ② 공장 품질 관리 절차 미흡 : 합/부 기준 및 Internal 검사 절차 부재 (Random Sample 검사 Only) - By Contractor ① Trial Fit 수량 불충분 : (Primary Riser Tip과 tile Hole간) alignment 검사 수량 선정 미흡으로 전반적인 품질 수준 판단 기회 상실 → Spec. 요건 (One per each type) 적용 시, 전체 수량 및 검사 중요도 고려 미흡 ② Licensor(Proprietary) 품목에 대한 품질 관리 방안 개선 요구 및 적용 애로 (검사 빈도, 수량 등) | V6: https://teams.microsoft.com/l/message/19:KlEVjYWGS-QmxCKqE5H4Ofn-AvSWTK6hz_ErP7aUdvg1@thread.tacv2/1770611467271?tenantId=5fcb0def-a698-40ce-a73a-ea61130c13c6&groupId=80bfa3ae-81fa-4e4e-ba65-7b9c876b82d8&parentMessageId=1770611467271&teamName=P-Quality%20Alert%20Notice%20(PQAN)&channelName=PQAN%20Library&createdTime=1770611467271
A7: =ROW()-1 -> 6 | B7: PQAN-2025-006 | C7: 45898 | D7: 2025 | E7: 8 | F7: 0 | G7: 유요석 | H7: 배관 | L7: Pipe Inside Surface Imperfection | M7: Carbon Steel Seamless Pipe | N7: Tenaris | O7: 이탈리아 | P7: DALMINE | Q7: After delivery (Site) | R7: Site | S7: 현장 입고 후 Pipe 외관 검사 중 내부 표면에서 Expanding Mark, Pit, Heavy Mill scale 등이 발견됨 | T7: Rotary expansion 공정 중 노후화로 마모된 Expanding Mandrel의 형상이 PIPE 내면에 전사되어 자국 형성 Pipe 생산 중 생성된 Mill scale 제거부위에 (후처리 공정) Pit 형상의 고르지 못한 Surface Imperfection 발생 수압 시험 중 떨어진 Scale이 완전 제거되지 않고 Pipe 벽면에 재 부착 & 두꺼운 Scale층 형성 Pipe 생산 중 열처리 (Normalizing, Quenching & Tempering 등)에 사용되는 연소 gas의 Oxygen content, Temperature 범위 & Holding Time 관리 불량 Pipe 생산 후처리 공정 중 내면 Blowing & Grinding 작업 미흡 | V7: https://teams.microsoft.com/l/message/19:KlEVjYWGS-QmxCKqE5H4Ofn-AvSWTK6hz_ErP7aUdvg1@thread.tacv2/1770611919162?tenantId=5fcb0def-a698-40ce-a73a-ea61130c13c6&groupId=80bfa3ae-81fa-4e4e-ba65-7b9c876b82d8&parentMessageId=1770611919162&teamName=P-Quality%20Alert%20Notice%20(PQAN)&channelName=PQAN%20Library&createdTime=1770611919162
A8: =ROW()-1 -> 7 | B8: PQAN-2025-007 | C8: 45930 | D8: 2025 | E8: 9 | F8: 0 | G8: 유요석 | H8: 전기 | L8: 변압기 탱크의 누유 | M8: Power Transformer | N8: 현대일렉트릭 | O8: 대한민국 | Q8: After delivery (Site) | R8: Site | S8: 현장 입고 된 변압기의 외부에서 Oil Leak 흔적이 발견됨 | T8: 공장 압력시험 (0.35kgf/㎠, 24시간 Holding) 중에는 Oil Leak 확인되지 않았으나 현장 인도/설치 이후 모래먼지 포집 흔적 등으로 Oil Leak가 발견되었고, 세부 조사 결과 변압기 Tank 제작 시 다수의 용접 결함이 발생한 것으로 확인됨 변압기 탱크 구조 및 형상 제한에 따른 용접 작업 애로 → 결함 발생 형식적인 용접부 외관 검사 및 비파괴 (PT) 수행으로 표면 용접결함 확인 실패 | V8: https://teams.microsoft.com/l/message/19:KlEVjYWGS-QmxCKqE5H4Ofn-AvSWTK6hz_ErP7aUdvg1@thread.tacv2/1770612108827?tenantId=5fcb0def-a698-40ce-a73a-ea61130c13c6&groupId=80bfa3ae-81fa-4e4e-ba65-7b9c876b82d8&parentMessageId=1770612108827&teamName=P-Quality%20Alert%20Notice%20(PQAN)&channelName=PQAN%20Library&createdTime=1770612108827
A9: =ROW()-1 -> 8 | B9: PQAN-2025-008 | C9: 45958 | D9: 2025 | E9: 10 | F9: 0 | G9: 유요석 | H9: 배관 | L9: Casting Valve - Stem Packing 누설 | M9: Casting Valve | N9: Neway | O9: 중국 | Q9: After delivery (Site) | R9: Site | S9: 모듈샵 수압시험 중 Casting Valve의 Stem Packing 부위에서 지속적으로 누설 발생함 | T9: 프로젝트 Piping Material Spec.은 451℃ ~ 800℃ 고온 조건만 고려하여 Packing 재질 (MICA or Equivalent)을 규정하고 있음 (압력 미 고려) Packing 재질로써 MICA만 적용할 경우, 재질 특성상 고온에는 강하지만 고압에서는 Sealing 성능이 저하될 수 있음 TBE 시 타 업체는 대안으로 MICA + α (적층구조)를 제시하였으나, 본 공급업체는 프로젝트 요구사항에 따른 MICA 단일 재질을 적용하였음 고압 (Class 2500) Valve에서 집중적으로 누설 발생  MICA + Graphite로 설계 변경 추진 | V9: https://teams.microsoft.com/l/message/19:KlEVjYWGS-QmxCKqE5H4Ofn-AvSWTK6hz_ErP7aUdvg1@thread.tacv2/1770612202349?tenantId=5fcb0def-a698-40ce-a73a-ea61130c13c6&groupId=80bfa3ae-81fa-4e4e-ba65-7b9c876b82d8&parentMessageId=1770612202349&teamName=P-Quality%20Alert%20Notice%20(PQAN)&channelName=PQAN%20Library&createdTime=1770612202349
A10: =ROW()-1 -> 9 | B10: PQAN-2025-009 | C10: 45989 | D10: 2025 | E10: 11 | F10: 0 | G10: 유요석 | H10: 전기 | L10: 애관 외관 결함 Bushing Surface Defect | M10: Bushing Insulator (Ceramic Type) | N10: 메인: 삼화컨덴서 제작: 태성 세라믹 조립: 남도전기 | O10: 대한민국 | Q10: After delivery (Site) | R10: Site | S10: -Power Capacitor의 현장 자재 인수 검사 중, 애관 표면에 Hole 형태의 외관 결함 발견됨 -Power Transformer의 현장 자재 인수 검사 중, 애관 표면에 Crack 발견됨 | T10: -Ceramic 애관 제작은 수작업으로 이뤄지며 (도자기 제작과 유사), 작업자 숙련도에 따라 제품 품질 상이 -애관 제작 관련 PJT Spec. / Code 요건이 계약에 반영되어 있지 않고 Vendor 자체 육안 검사(형식적) 외에 품질관리 요건 미적용 (KS 3801 / 3802, IEC 60137 등 관련 Code 있으나 전기 Item의 Sub-sub component로 품질 관리 대상에서 제외됨) -애관 설치 시, Over torque 적용 / Bolt 체결 순서 미 준수 / Clamp 모서리 Notch에 애관이 눌리며 Crack 발생 | V10: https://teams.microsoft.com/l/message/19:KlEVjYWGS-QmxCKqE5H4Ofn-AvSWTK6hz_ErP7aUdvg1@thread.tacv2/1770612284366?tenantId=5fcb0def-a698-40ce-a73a-ea61130c13c6&groupId=80bfa3ae-81fa-4e4e-ba65-7b9c876b82d8&parentMessageId=1770612284366&teamName=P-Quality%20Alert%20Notice%20(PQAN)&channelName=PQAN%20Library&createdTime=1770612284366
A11: =ROW()-1 -> 10 | B11: PQAN-2025-010 | C11: 46021 | D11: 2025 | E11: 12 | F11: 1 | G11: 유요석 | H11: 장치 | L11: 열교환기 내부의 수압시험 잔류수/응축수 | M11: 열교환기 | N11: 중국: Dongfang 미국: Chromalox 한국: | O11: 대한민국/중국/미국 | Q11: After delivery (Site) | R11: Site | S11: -열교환기의 현장 자재 인수 검사 중, 기기 내부에서 수압시험 잔류수 또는 부적절한 N2 Purging에 따른 응축수 발견됨 -수압시험 잔류수 / 응축수의 장기 노출에 따른 Shell / Tube side에 Rust contamination 발생함 | T11: -기기 configuration을 고려한 Drain 절차 미수립으로 (Floating Head 하단과 tubesheet의 높이차 미고려) 수압시험 잔류수 잔존 -Drain & Dry out 후 부적절한 검사 수행 (Borescope 등을 활용한 기기 내부 잔류수 확인 절차 미적용) -수압시험 시 녹 발생 방지용 Inhibitor 미적용 -부적절한 N2 Purging 수행 (N2 Purging 반복 : Air → N2 치환) 및 기기 내부 이슬점 온도 미확인 | V11: https://teams.microsoft.com/l/message/19:KlEVjYWGS-QmxCKqE5H4Ofn-AvSWTK6hz_ErP7aUdvg1@thread.tacv2/1770612400616?tenantId=5fcb0def-a698-40ce-a73a-ea61130c13c6&groupId=80bfa3ae-81fa-4e4e-ba65-7b9c876b82d8&parentMessageId=1770612400616&teamName=P-Quality%20Alert%20Notice%20(PQAN)&channelName=PQAN%20Library&createdTime=1770612400616
A12: =ROW()-1 -> 11 | B12: PQAN-2026-001 | C12: 46050 | D12: 2026 | E12: 1 | F12: 0 | G12: 유요석 | H12: 장치 | L12: 도장 색상 불일치 | M12: Deaerator | N12: Stork | O12: 네덜란드 | Q12: Painting Inspection | R12: Vendor | S12: 도장 검사 중 일부 기자재의 Final 도장 색상이 요구 사항과 상이함이 발견됨 Deaerator Saddle Part (요구사항: RAL 7042 / 실제적용: RAL 7032) Power Distribution Board (요구사항: RAL 7042 / 실제적용: RAL 7035) | T12: -도장 제조사 / International의 Silicone Acrylic 계열 도장재의 가용 색상(RAL 7042) 확인 없이 절차서 작성, 유사 색상(RAL7032) 임의 적용 -도장 사양 및 도장절차서 상에 명기되어 있는 색상 확인 절차 누락 | U12: -도장절차서 제출 시, 제조사 Datasheet + 색상 가용 확인 Letter 검토 -검사 시, RAL-Munsell Code 활용 의무화 (MR 반영) | V12: https://teams.microsoft.com/l/message/19:KlEVjYWGS-QmxCKqE5H4Ofn-AvSWTK6hz_ErP7aUdvg1@thread.tacv2/1770612649076?tenantId=5fcb0def-a698-40ce-a73a-ea61130c13c6&groupId=80bfa3ae-81fa-4e4e-ba65-7b9c876b82d8&parentMessageId=1770612649076&teamName=P-Quality%20Alert%20Notice%20(PQAN)&channelName=PQAN%20Library&createdTime=1770612649076
A13: =ROW()-1 -> 12 | B13: PQAN-2026-001 | C13: 46050 | D13: 2026 | E13: 1 | F13: 0 | G13: 유요석 | H13: 전기 | L13: 도장 색상 불일치 | M13: Power Distribution Board | N13: Al-Fanar | O13: 사우디아라비아 | Q13: Painting Inspection | R13: Vendor | S13: 도장 검사 중 일부 기자재의 Final 도장 색상이 요구 사항과 상이함이 발견됨 Deaerator Saddle Part (요구사항: RAL 7042 / 실제적용: RAL 7032) Power Distribution Board (요구사항: RAL 7042 / 실제적용: RAL 7035) | T13: -도장 제조사 / International의 Silicone Acrylic 계열 도장재의 가용 색상(RAL 7042) 확인 없이 절차서 작성, 유사 색상(RAL7032) 임의 적용 -도장 사양 및 도장절차서 상에 명기되어 있는 색상 확인 절차 누락 | U13: -도장절차서 제출 시, 제조사 Datasheet + 색상 가용 확인 Letter 검토 -검사 시, RAL-Munsell Code 활용 의무화 (MR 반영) | V13: https://teams.microsoft.com/l/message/19:KlEVjYWGS-QmxCKqE5H4Ofn-AvSWTK6hz_ErP7aUdvg1@thread.tacv2/1770612649076?tenantId=5fcb0def-a698-40ce-a73a-ea61130c13c6&groupId=80bfa3ae-81fa-4e4e-ba65-7b9c876b82d8&parentMessageId=1770612649076&teamName=P-Quality%20Alert%20Notice%20(PQAN)&channelName=PQAN%20Library&createdTime=1770612649076
A14: =ROW()-1 -> 13 | B14: PQAN-2026-002 | C14: 46078 | D14: 2026 | E14: 2 | F14: 0 | G14: 유요석 | H14: 회전 | L14: Pump Casing 주조결함 (1. Pump Casing Casting 결함) | M14: Centrifugal Pump | N14: Flowserve / Peekay Steel | O14: 인도 | Q14: Visual Inspection | R14: Vendor | S14: Super Duplex Stainless Steel (SDSS)로 제작된 Pump Casing의 Casting 결함에 따른 Pump 제작 지연 및 시운전 중 Leak 발생 | T14: -Casting 결함 – Porosity, Shrinkage, Crack 등 - Casting 전, Pump Model별 Pattern 및 주조 관리 역량 검증 미흡 | U14: -NORSOK M-650 Certificate 등 Casting Foundry 제조 역량 사전 검증 -신규 Pattern에 대해 주물 유동, 응고 해석 등 주조 관리 방안 시뮬레이션 검증 -SDSS 용접 보수 시, Post-Weld Heat Treatment 적용 | V14: https://teams.microsoft.com/l/message/19:KlEVjYWGS-QmxCKqE5H4Ofn-AvSWTK6hz_ErP7aUdvg1@thread.tacv2/1771985386124?tenantId=5fcb0def-a698-40ce-a73a-ea61130c13c6&groupId=80bfa3ae-81fa-4e4e-ba65-7b9c876b82d8&parentMessageId=1771985386124&teamName=P-Quality%20Alert%20Notice%20(PQAN)&channelName=PQAN%20Library&createdTime=1771985386124
A15: =ROW()-1 -> 14 | B15: PQAN-2026-002 | C15: 46078 | D15: 2026 | E15: 2 | F15: 0 | G15: 유요석 | H15: 회전 | L15: Pump Casing 주조결함 (2. Casting Cleaning window 관리) | M15: Centrifugal Pump | N15: Sulzer Saudi / Ultimate Alloy | O15: 사우디아라비아 | Q15: After delivery (Site) | R15: Site | S15: Super Duplex Stainless Steel (SDSS)로 제작된 Pump Casing의 Casting 결함에 따른 Pump 제작 지연 및 시운전 중 Leak 발생 | T15: -Cleaning Window 임의 적용 - Casting 단계에서 Cleaning Window 적용 여부 미확인 | U15: -제작 전, Casing에 Cleaning Window 적용 여부 확인 -Cleaning Window 적용 시, Window Closing을 위한 WPS/PQR, Welding Map 검토 및 용접부 건전성 확인 (UT / RT) | V15: https://teams.microsoft.com/l/message/19:KlEVjYWGS-QmxCKqE5H4Ofn-AvSWTK6hz_ErP7aUdvg1@thread.tacv2/1771985386124?tenantId=5fcb0def-a698-40ce-a73a-ea61130c13c6&groupId=80bfa3ae-81fa-4e4e-ba65-7b9c876b82d8&parentMessageId=1771985386124&teamName=P-Quality%20Alert%20Notice%20(PQAN)&channelName=PQAN%20Library&createdTime=1771985386124
A16: =ROW()-1 -> 15 | B16: PQAN-2026-003 | C16: 46104 | D16: 2026 | E16: 3 | F16: 0 | G16: 유요석 | H16: 배관 | L16: Oxygen Service Valve의 Cleanliness 요건 불만족(EIGA 33) - 포장손상 | M16: Forged Valve (Oxygen Servie) | N16: OMB | O16: 이탈리아 | Q16: After delivery (Site) | R16: Site | S16: Oxygen Valve에 대한 현장 자재인수검사 중 포장 손상, 밀봉 손상, 표면 오염이 발견되었고, 이는 EIGA Doc 33/18에 따라 확보한 Cleanliness의 훼손을 의미함 ※ EIGA Doc 33/18, Para. 10: Clean Room에서 Cleanliness 검사 완료 직후 오염 방지를 위한 밀봉 작업이 이루어져야 함 | T16: Cleanliness Requirements를 고려하지 않은 Packing Method 적용 - 개별 Seal Packing 손상 방지를 위한 Wooden Box – Valve 간 보호조치 미흡 - Valve 간 충돌 방지를 위한 보호조치 및 충분한 이격거리 미확보 (밀집 포장) Valve 외부 표면 오염 - Seal Packing 손상 또는 Seal Packing 작업 미흡으로 인해 산소 유입 - Valve 표면에 흡착된 철가루가 산화하여 녹 발생 추정 | U16: 개별 Seal Packing 등 내부 손상 방지를 위한 Packing Procedure 수립 및 이행 - Valve – Valve, Wooden Box – Valve 간 Protection 방안 (Ex. Seal Packing - Bubble Wrap 이중포장) - Nail이 아닌 Screw를 사용한 Boxing 작업 수행 Vendor 반송 (Vendor Guarantee) & 하기 검사항목 100% 입회검사 진행 (by TPI) - Cleaning & Cleanliness Inspection / Seal Packing Process (at Clean Room) - Packing (Wooden Box Closing) Inspection | V16: https://teams.microsoft.com/l/message/19:KlEVjYWGS-QmxCKqE5H4Ofn-AvSWTK6hz_ErP7aUdvg1@thread.tacv2/1774231397159?tenantId=5fcb0def-a698-40ce-a73a-ea61130c13c6&groupId=80bfa3ae-81fa-4e4e-ba65-7b9c876b82d8&parentMessageId=1774231397159&teamName=P-Quality%20Alert%20Notice%20(PQAN)&channelName=PQAN%20Library&createdTime=1774231397159
A17: =ROW()-1 -> 16 | B17: PQAN-2026-004 | C17: 46132 | D17: 2026 | E17: 4 | F17: 0 | G17: 유요석 | H17: 철골 | L17: Steel Structure 도장 박리 | M17: Steel Structure | N17: KIC | O17: 대한민국 | Q17: After delivery (Site) | R17: Site | S17: 배관 Spool & 철골 도장 후 자재 인수검사 / 현장설치 후 도장박리 발생으로 Bare Steel 노출 | T17: 일반 Inorganic Zinc 도료는 상대적으로 높은 온도와 습도 조건에서 경화 성능 발현 - 동절기 저온/저습 환경에서 경화 지연 및 경화 시간 불충분으로 불완전 경화 Inorganic Zinc Primer Coat의 불완전 경화 (Curing)로 인한 Substrate와의 계면 접착력 저하 Intermediate Coat의 경화 (Curing) 과정에서 발생한 수축 응력이 불완전 경화된 Primer Coat에 인장 응력으로 작용하여 계면 박리 발생 (철골) | U17: Paint Maker의 Technical Data Sheet (TDS) 및 Application Guide의 도장 요건 준수 계절별 충분한 온도/습도 및 경화시간 확보 Inorganic Zinc의 불완전 경화가 의심되는 경우 MEK Test 실시 Substrate 표면처리 적합성 확인 검사 수행 - Press O Film Test, Dust Test, Salt Contamination Test Production Paint 수행 전 Paint Panel Test (Mock-up Test) 수행 | V17: https://teams.microsoft.com/l/message/19:KlEVjYWGS-QmxCKqE5H4Ofn-AvSWTK6hz_ErP7aUdvg1@thread.tacv2/1776662000956?tenantId=5fcb0def-a698-40ce-a73a-ea61130c13c6&groupId=80bfa3ae-81fa-4e4e-ba65-7b9c876b82d8&parentMessageId=1776662000956&teamName=P-Quality%20Alert%20Notice%20(PQAN)&channelName=PQAN%20Library&createdTime=1776662000956

Sheet TPA_목록
A1: 순번 | B1: TPA | C1: 등록평가 | D1: 정기평가 (2023) | E1: 정기평가 (2024) | F1: 정기평가 (2025) | G1: 정기평가 (2026)
A2: =ROW()-1 -> 1 | B2: 3P | C2: 71 | F2: N/A (2025 실적 없음)
A3: =ROW()-1 -> 2 | B3: A&A | C3: 85 | F3: 93.3
A4: =ROW()-1 -> 3 | B4: ACES | C4: 100 | F4: 80.8
A5: =ROW()-1 -> 4 | B5: APAVE | C5: 93.5 | F5: 90.7
A6: =ROW()-1 -> 5 | B6: APPLUS | C6: 94 | F6: 92.3
A7: =ROW()-1 -> 6 | B7: BROOKE | C7: 74 | F7: N/A (2025 실적 없음)
A8: =ROW()-1 -> 7 | B8: BV | C8: 91 | F8: 88.4
A9: =ROW()-1 -> 8 | B9: DNV | C9: 91 | F9: 91.7
A10: =ROW()-1 -> 9 | B10: ERAM | C10: 100 | F10: 93.1
A11: =ROW()-1 -> 10 | B11: FE | C11: 74 | F11: 76.3
A12: =ROW()-1 -> 11 | B12: GISCO | C12: 89 | F12: 84.3
A13: =ROW()-1 -> 12 | B13: GOODIN | C13: 98 | F13: 85.2
A14: =ROW()-1 -> 13 | B14: INTERTEK | C14: 100 | F14: 92.4
A15: =ROW()-1 -> 14 | B15: KOTEC | C15: 95.5 | F15: 82.1
A16: =ROW()-1 -> 15 | B16: PETRO-Q | C16: 74 | F16: 71.4
A17: =ROW()-1 -> 16 | B17: PETROZONE | C17: 80 | F17: 81.9
A18: =ROW()-1 -> 17 | B18: RINA | C18: 98 | F18: 79.3
A19: =ROW()-1 -> 18 | B19: SGS | C19: 98 | F19: 81.9
A20: =ROW()-1 -> 19 | B20: TEXIN | C20: 100 | F20: N/A (2025 실적 없음)
A21: =ROW()-1 -> 20 | B21: TQ CERT | C21: 85 | F21: N/A (2025 실적 없음)
A22: =ROW()-1 -> 21 | B22: TECHNOCRAT | C22: 83 | F22: 75.2
A23: =ROW()-1 -> 22 | B23: TUV NORD | C23: 100 | F23: N/A (2025 실적 없음)
A24: =ROW()-1 -> 23 | B24: TUV RHEINLAND | C24: 94 | F24: N/A (2025 실적 없음)
A25: =ROW()-1 -> 24 | B25: ACE PLANTECH | C25: 96.5 | F25: N/A (2025 실적 없음)
A26: =ROW()-1 -> 25 | B26: AMO | C26: 89 | F26: N/A (2025 실적 없음)
A27: =ROW()-1 -> 26 | B27: HEBO | C27: 80 | F27: N/A (2025 실적 없음)
A28: =ROW()-1 -> 27 | B28: SITCO | C28: 94 | F28: N/A (2025 실적 없음)

Sheet TPA_집행현황
A1: 프로젝트 | B1: 단계 | C1: TPA 예산 (USD) | D1: TPA 계약고 (USD) | E1: 집행비용 (USD) | F1: TPA 예산 (KRW) | G1: TPA 계약고 (KRW) | H1: 집행비용 (KRW) | I1: 예산 소진율 | J1: 現 계약고 소진율
A2: MIP6 | B2: Mechanical Completion | C2: 12511157 | D2: 12511157 | E2: =SUMIF(TPA_월별대금청구현황!$B$2:$B$2009,TPA_집행현황!$A2,TPA_월별대금청구현황!$E$2:$E$2009) -> 12499872 | I2: =E2/C2 -> 0.99909802 | J2: =E2/D2 -> 0.99909802
A3: SM12 | B3: Active | C3: 9017286 | D3: 9017286 | E3: =SUMIF(TPA_월별대금청구현황!$B$2:$B$2009,TPA_집행현황!$A3,TPA_월별대금청구현황!$E$2:$E$2009) -> 8978506.2 | I3: =E3/C3 -> 0.99569939 | J3: =E3/D3 -> 0.99569939
A4: IBRU | B4: Mechanical Completion | C4: 4024396 | D4: 2886653.2 | E4: =SUMIF(TPA_월별대금청구현황!$B$2:$B$2009,TPA_집행현황!$A4,TPA_월별대금청구현황!$E$2:$E$2009) -> 2588452.4 | I4: =E4/C4 -> 0.64319029 | J4: =E4/D4 -> 0.89669671
A5: SHN1 | B5: Active | F5: 3442862995 | G5: 3384427737 | H5: =SUMIF(TPA_월별대금청구현황!$B$2:$B$2009,TPA_집행현황!$A5,TPA_월별대금청구현황!$E$2:$E$2009) -> 2.6466715e+09 | I5: =H5/F5 -> 0.76874145 | J5: =H5/G5 -> 0.78201448
A6: ALOM | B6: Active | C6: 766265 | D6: 766265 | E6: =SUMIF(TPA_월별대금청구현황!$B$2:$B$2009,TPA_집행현황!$A6,TPA_월별대금청구현황!$E$2:$E$2009) -> 410205.2 | I6: =E6/C6 -> 0.53533073 | J6: =E6/D6 -> 0.53533073
A7: VEQU | B7: Active | C7: 375828 | D7: 228937 | E7: =SUMIF(TPA_월별대금청구현황!$B$2:$B$2009,TPA_집행현황!$A7,TPA_월별대금청구현황!$E$2:$E$2009) -> 203612.28 | I7: =E7/C7 -> 0.54176985 | J7: =E7/D7 -> 0.88938127
A8: STA4 | B8: Active | C8: 8945512 | D8: =6660845.4+801807.6 -> 7462653 | E8: =SUMIF(TPA_월별대금청구현황!$B$2:$B$2009,TPA_집행현황!$A8,TPA_월별대금청구현황!$E$2:$E$2009) -> 6714860 | I8: =E8/C8 -> 0.7506401 | J8: =E8/D8 -> 0.89979529
A9: SAC2 | B9: Active | C9: 4791851 | D9: =3590000+60000 -> 3650000 | E9: =SUMIF(TPA_월별대금청구현황!$B$2:$B$2009,TPA_집행현황!$A9,TPA_월별대금청구현황!$E$2:$E$2009) -> 2747125.7 | I9: =E9/C9 -> 0.57329113 | J9: =E9/D9 -> 0.75263717
A10: CSSP | B10: Active | C10: 5960701 | D10: 미정 | I10: =E10/C10 -> 0 | J10: N/A
A11: PNG1 | B11: Active | C11: 1875089 | D11: 미정 | I11: =E11/C11 -> 0 | J11: N/A
A12: ALSM | B12: Bid | C12: 미정 | D12: 미정 | I12: N/A | J12: N/A

Sheet TPA_월별대금청구현황
A1: 순번 | B1: 프로젝트 | C1: TPA | D1: 청구연월 | E1: 지급대금 | F1: 단위
A2: =ROW()-1 -> 1
A3: =ROW()-1 -> 2
A4: =ROW()-1 -> 3 | B4: ALOM | C4: DNV | D4: 46113 | E4: 36355 | F4: USD
A5: =ROW()-1 -> 4 | B5: VEQU | C5: APPLUS | D5: 46113 | E5: 188 | F5: USD
A6: =ROW()-1 -> 5 | B6: SHN1 | C6: GOODIN | D6: 46113 | E6: 237000 | F6: KRW
A7: =ROW()-1 -> 6 | B7: SHN1 | C7: A&A | D7: 46113 | E7: 12694676 | F7: KRW
A8: =ROW()-1 -> 7 | B8: SHN1 | C8: DNV | D8: 46113 | E8: 129437262 | F8: KRW
A9: =ROW()-1 -> 8 | B9: STA4 | C9: DNV | D9: 46113 | E9: 49502.3 | F9: USD
A10: =ROW()-1 -> 9 | B10: STA4 | C10: RINA | D10: 46113 | E10: 111120.56 | F10: USD
A11: =ROW()-1 -> 10 | B11: STA4 | C11: INTERTEK | D11: 46113 | E11: 22723.67 | F11: USD
A12: =ROW()-1 -> 11 | B12: STA4 | C12: ERAM | D12: 46113 | E12: 83403.18 | F12: USD
A13: =ROW()-1 -> 12 | B13: STA4 | C13: PETROZONE | D13: 46113 | E13: 59880 | F13: USD
A14: =ROW()-1 -> 13 | B14: STA4 | C14: FE | D14: 46113 | E14: 45544.28 | F14: USD
A15: =ROW()-1 -> 14 | B15: STA4 | C15: ACES | D15: 46113 | E15: 30876.25 | F15: USD
... A1409: =ROW()-1 -> 1408 | B1409: SM12 | C1409: INTERTEK | D1409: 43831 | E1409: 3696 | F1409: USD

Sheet 인력운영_현황
A1: 순번 | B1: 이름 | C1: 소속 | D1: 근무지 | E1: 직급 | F1: 파트 | G1: 담당 공종 | H1: PQCM | I1: PQC_Engineer | J1: Number_of_PO
A2: =ROW()-1 -> 1 | B2: 유요석 팀장 | C2: 플랜트구매품질팀 | D2: 본사 | E2: G3 | J2: 해당없음
A3: =ROW()-1 -> 2 | B3: 강택기 책임 | C3: 플랜트구매품질팀 | D3: 본사 | E3: G3 | F3: 배관 | G3: Piping | I3: SAC2 / VEQU | J3: =COUNTIFS(인력운영_세부내역!$J$2:$J$1500,인력운영_현황!$B3,인력운영_세부내역!$G$2:$G$1500,"<>완료",인력운영_세부내역!$G$2:$G$1500,"<>NA") -> 9
A4: =ROW()-1 -> 3 | B4: 윤희수 책임 | C4: 플랜트구매품질팀 | D4: 본사 | E4: G3 | F4: 전기/계장 | G4: Electrical & Instrument | H4: ALOM / VEQU | I4: STA4 / ALOM / CSSP | J4: =COUNTIFS(인력운영_세부내역!$J$2:$J$1500,인력운영_현황!$B4,인력운영_세부내역!$G$2:$G$1500,"<>완료",인력운영_세부내역!$G$2:$G$1500,"<>NA") -> 42
A5: =ROW()-1 -> 4 | B5: 서민 책임 | C5: 플랜트구매품질팀 | D5: 본사 | E5: G3 | F5: 회전기계 | G5: Rotating | I5: STA4 / CSSP / PNG1 | J5: =COUNTIFS(인력운영_세부내역!$J$2:$J$1500,인력운영_현황!$B5,인력운영_세부내역!$G$2:$G$1500,"<>완료",인력운영_세부내역!$G$2:$G$1500,"<>NA") -> 46
A6: =ROW()-1 -> 5 | B6: 장동철 책임 | C6: 플랜트구매품질팀 | D6: 본사 | E6: G3 | F6: 배관 | G6: Rotating / Piping | H6: SM12 | I6: SM12 / IBRU / CSSP / PNG1 | J6: =COUNTIFS(인력운영_세부내역!$J$2:$J$1500,인력운영_현황!$B6,인력운영_세부내역!$G$2:$G$1500,"<>완료",인력운영_세부내역!$G$2:$G$1500,"<>NA") -> 43
A7: =ROW()-1 -> 6 | B7: 정진우 책임 | C7: 플랜트구매품질팀 | D7: 본사 | E7: G3 | F7: 장치기계 | G7: Static | H7: CSSP | I7: SM12 / ALOM / CSSP | J7: =COUNTIFS(인력운영_세부내역!$J$2:$J$1500,인력운영_현황!$B7,인력운영_세부내역!$G$2:$G$1500,"<>완료",인력운영_세부내역!$G$2:$G$1500,"<>NA") -> 11
A8: =ROW()-1 -> 7 | B8: 나광조 책임 | C8: 플랜트구매품질팀 | D8: 본사 | E8: G2 | F8: 장치기계 | G8: Static | I8: SHN1 / ALOM / CSSP / PNG1 | J8: =COUNTIFS(인력운영_세부내역!$J$2:$J$1500,인력운영_현황!$B8,인력운영_세부내역!$G$2:$G$1500,"<>완료",인력운영_세부내역!$G$2:$G$1500,"<>NA") -> 16
A9: =ROW()-1 -> 8 | B9: 강태준 책임 | C9: 플랜트구매품질팀 | D9: 본사 | E9: G2 | F9: 전략기획 | G9: Rotating / Piping | H9: PNG1 / ALSM | I9: VEQU / CSSP / PNG1 | J9: =COUNTIFS(인력운영_세부내역!$J$2:$J$1500,인력운영_현황!$B9,인력운영_세부내역!$G$2:$G$1500,"<>완료",인력운영_세부내역!$G$2:$G$1500,"<>NA") -> 39
A10: =ROW()-1 -> 9 | B10: 이해석 책임 | C10: 플랜트구매품질팀 | D10: 본사 | E10: G2 | F10: 전기/계장 | G10: Electrical & Instrument | H10: SHN1 | I10: STA4 / SHN1 | J10: =COUNTIFS(인력운영_세부내역!$J$2:$J$1500,인력운영_현황!$B10,인력운영_세부내역!$G$2:$G$1500,"<>완료",인력운영_세부내역!$G$2:$G$1500,"<>NA") -> 21
A11: =ROW()-1 -> 10 | B11: 최종현 책임 | C11: 플랜트구매품질팀 | D11: 본사 | E11: G2 | F11: 전기/계장 | G11: Electrical & Instrument | H11: SAC2 | I11: SAC2 | J11: =COUNTIFS(인력운영_세부내역!$J$2:$J$1500,인력운영_현황!$B11,인력운영_세부내역!$G$2:$G$1500,"<>완료",인력운영_세부내역!$G$2:$G$1500,"<>NA") -> 17
A12: =ROW()-1 -> 11 | B12: 석우경 매니저 | C12: 플랜트구매품질팀 | D12: 본사 | E12: G1 | F12: 배관 | G12: Piping | I12: ALOM / CSSP / PNG1 | J12: =COUNTIFS(인력운영_세부내역!$J$2:$J$1500,인력운영_현황!$B12,인력운영_세부내역!$G$2:$G$1500,"<>완료",인력운영_세부내역!$G$2:$G$1500,"<>NA") -> 53
A13: =ROW()-1 -> 12 | B13: 고팔라크리스낸 매니저 | C13: 플랜트구매품질팀 | D13: 본사 | E13: GS | F13: 철골 | G13: Static / Structural Steel | I13: STA4 / VEQU / CSSP / PNG1 | J13: =COUNTIFS(인력운영_세부내역!$J$2:$J$1500,인력운영_현황!$B13,인력운영_세부내역!$G$2:$G$1500,"<>완료",인력운영_세부내역!$G$2:$G$1500,"<>NA") -> 20
A14: =ROW()-1 -> 13 | B14: 술탄 매니저 | C14: 플랜트구매품질팀 | D14: 본사 | E14: GS | F14: 전기/계장 | G14: Electrical & Instrument | I14: VEQU / CSSP | J14: =COUNTIFS(인력운영_세부내역!$J$2:$J$1500,인력운영_현황!$B14,인력운영_세부내역!$G$2:$G$1500,"<>완료",인력운영_세부내역!$G$2:$G$1500,"<>NA") -> 24
A15: =ROW()-1 -> 14 | B15: 엥흐철멍 매니저 | C15: 플랜트구매품질팀 | D15: 본사 | E15: GS | F15: 배관 | G15: Piping | I15: PNG1 | J15: =COUNTIFS(인력운영_세부내역!$J$2:$J$1500,인력운영_현황!$B15,인력운영_세부내역!$G$2:$G$1500,"<>완료",인력운영_세부내역!$G$2:$G$1500,"<>NA") -> 1
A16: =ROW()-1 -> 15 | B16: 최우석 책임 | C16: STA4 | D16: 현장 | E16: G3 | F16: 장치기계 | H16: STA4 | J16: 해당없음
A17: =ROW()-1 -> 16 | B17: 강인묵 책임 | C17: STA4 | D17: 서울사무소 | E17: G2 | F17: 전기/계장 | G17: Electrical & Instrument | I17: STA4 / CSSP | J17: =COUNTIFS(인력운영_세부내역!$J$2:$J$1500,인력운영_현황!$B17,인력운영_세부내역!$G$2:$G$1500,"<>완료",인력운영_세부내역!$G$2:$G$1500,"<>NA") -> 28
A18: =ROW()-1 -> 17 | B18: 최영준 책임 | C18: STA4 | D18: 현장 | E18: G2 | F18: 장치기계 | G18: Static | I18: STA4 | J18: =COUNTIFS(인력운영_세부내역!$J$2:$J$1500,인력운영_현황!$B18,인력운영_세부내역!$G$2:$G$1500,"<>완료",인력운영_세부내역!$G$2:$G$1500,"<>NA") -> 8
A19: =ROW()-1 -> 18 | B19: 임효원 책임 | C19: STA4 | D19: 현장 | E19: P6 | F19: 배관 | G19: Piping | I19: STA4 | J19: =COUNTIFS(인력운영_세부내역!$J$2:$J$1500,인력운영_현황!$B19,인력운영_세부내역!$G$2:$G$1500,"<>완료",인력운영_세부내역!$G$2:$G$1500,"<>NA") -> 37
A20: =ROW()-1 -> 19 | B20: 황윤섭 책임 | C20: SAC2 | D20: 현장 | E20: P5 | F20: 배관 | G20: Piping | I20: SAC2 | J20: =COUNTIFS(인력운영_세부내역!$J$2:$J$1500,인력운영_현황!$B20,인력운영_세부내역!$G$2:$G$1500,"<>완료",인력운영_세부내역!$G$2:$G$1500,"<>NA") -> 13
A21: =ROW()-1 -> 20 | B21: 조상래 매니저 | C21: SAC2 | D21: 현장 | E21: G1 | F21: 전기/계장 | G21: 시공품질 | J21: 해당없음
A22: =ROW()-1 -> 21 | B22: 박지애 매니저 | C22: SAC2 | D22: 서울사무소 | E22: P2 | F22: 배관 | G22: Piping | I22: SAC2 | J22: =COUNTIFS(인력운영_세부내역!$J$2:$J$1500,인력운영_현황!$B22,인력운영_세부내역!$G$2:$G$1500,"<>완료",인력운영_세부내역!$G$2:$G$1500,"<>NA") -> 12
A23: =ROW()-1 -> 22 | B23: 박재석 책임 | C23: SHN1 | D23: 현장 | E23: P6 | F23: 장치기계 | G23: Static | I23: SHN1 | J23: =COUNTIFS(인력운영_세부내역!$J$2:$J$1500,인력운영_현황!$B23,인력운영_세부내역!$G$2:$G$1500,"<>완료",인력운영_세부내역!$G$2:$G$1500,"<>NA") -> 1
A24: =ROW()-1 -> 23 | B24: 유녕희 매니저 | C24: STA4 | D24: 서울사무소 | E24: P3 | G24: Inspection Coordinator | J24: 해당없음
A25: =ROW()-1 -> 24 | B25: 최보윤 매니저 | C25: STA4 | D25: 서울사무소 | E25: P1 | G25: Inspection Coordinator | J25: 해당없음
A26: =ROW()-1 -> 25 | B26: 성유진 매니저 | C26: SAC2 | D26: 서울사무소 | E26: P1 | G26: Inspection Coordinator | J26: 해당없음

Sheet 인력운영_세부내역
A1: 순번 | B1: 프로젝트 | C1: 공종 | D1: PO | E1: PO Description | F1: Quantity | G1: 업무 종료 예상 시기 | H1: IRC % | I1: 비고 | J1: 담당자(정) | K1: 담당자(부)
A2: =ROW()-2 -> 0 | B2: STA4 | C2: 장치 | D2: MS001 | E2: PRESSURE VESSEL I | F2: 12 ea | G2: 46172 | H2: 0.86 | J2: 고팔라크리스낸 매니저 | K2: 최영준 책임
A3: =ROW()-2 -> 1 | B3: STA4 | C3: 장치 | D3: MS002 | E3: PRESSURE VESSEL II | F3: 13 ea | G3: 46203 | H3: 0.73 | J3: 고팔라크리스낸 매니저 | K3: 최영준 책임
A4: =ROW()-2 -> 2 | B4: STA4 | C4: 장치 | D4: MS003 | E4: PRESSURE VESSEL III | F4: 1 ea | G4: 완료 | H4: 1 | J4: 고팔라크리스낸 매니저 | K4: 최영준 책임
A5: =ROW()-2 -> 3 | B5: STA4 | C5: 장치 | D5: MS004 | E5: FILTER | F5: 7 ea | G5: 완료 | H5: 1 | I5: IDR 작성/제출 완료, VIRB 제출완료 / 서류 종료 26.03 | J5: 최영준 책임 | K5: 정진우
A6: =ROW()-2 -> 4 | B6: STA4 | C6: 장치 | D6: MS005 | E6: SHELL AND TUBE HEAT EXCHANGER | F6: 3 ea | G6: 46203 | H6: 0.95 | J6: 고팔라크리스낸 매니저 | K6: 최영준 책임
A7: =ROW()-2 -> 5 | B7: STA4 | C7: 장치 | D7: MS006 | E7: AIR COOLED HEAT EXCHANGER | G7: 완료 | H7: 1 | I7: IDR 제출완료/VIRB 제출완료 / 서류 종료 예상시기 26.03 | J7: 최영준 책임 | K7: 고팔라크리스낸 매니저
A8: =ROW()-2 -> 6 | B8: STA4 | C8: 장치 | D8: MS007 | E8: PLATE & FRAME HEAT EXCHANGER | G8: 완료 | H8: 1 | J8: 최영준 책임 | K8: 고팔라크리스낸 매니저
A9: =ROW()-2 -> 7 | B9: STA4 | C9: 장치 | D9: MS008 | E9: SALINE COOLING WATER FILTER PACKAGE | F9: 33 ea | G9: 46142 | H9: 1 | I9: IDR 필요없음 (Inspection Level 3) / AET Procedure 발주처 승인 완료 / VIRB 진행 필요(현재 미접수) / 서류 종료 예상시기 26.04 | J9: 최영준 책임 | K9: 정진우 책임
A10: =ROW()-2 -> 8 | B10: STA4 | C10: 장치 | D10: MS011 | E10: STORAGE TANK | F10: 17 ea | G10: 46295 | H10: 0.46 | J10: 고팔라크리스낸 매니저 | K10: 최영준 책임
A11: =ROW()-2 -> 9 | B11: STA4 | C11: 장치 | D11: MS012 | E11: EDUCTOR | G11: 완료 | H11: 1 | I11: IDR 필요없음 / VIRB 제출완료 | J11: 최영준 책임 | K11: 고팔라크리스낸 매니저
A12: =ROW()-2 -> 10 | B12: STA4 | C12: 장치 | D12: MS013 | E12: STATIC MIXER | G12: 완료 | H12: 1 | I12: IDR 필요없음 / VIRB 제출완료 | J12: 최영준 책임 | K12: 고팔라크리스낸 매니저
A13: =ROW()-2 -> 11 | B13: STA4 | C13: 장치 | D13: MS014 | E13: DESUPER HEATER | G13: 완료 | H13: 1 | I13: IDR 체출완료 / VIRB 제출완료 | J13: 최영준 책임 | K13: 고팔라크리스낸 매니저
A14: =ROW()-2 -> 12 | B14: STA4 | C14: 장치 | D14: MS015 | E14: SILENCER | G14: 완료 | H14: NA | I14: Non inspectable | J14: 최영준 책임 | K14: 고팔라크리스낸 매니저
A15: =ROW()-2 -> 13 | B15: STA4 | C15: 장치 | D15: MS016 | E15: DEAERATOR | F15: 1 ea | G15: 46142 | H15: 1 | I15: IDR 작성/제출 필요, VIRB 접수(26.04.08) / 서류 종료 예상시기 26.04 | J15: 최영준 책임 | K15: 정진우 책임
A16: =ROW()-2 -> 14 | B16: STA4 | C16: 장치 | D16: MS017 | E16: AIR DRYER PACKAGE | F16: AIR DRYER PACKAGE 1 lot | G16: 46142 | H16: 1 | I16: Loose Supplied Valve 검사 완료 | J16: 최영준 책임 | K16: 고팔라크리스낸 매니저
A17: =ROW()-2 -> 15 | B17: STA4 | C17: 장치 | D17: MS018 | E17: LIN STORAGE & VAPORIZATION SYSTEM | F17: LIN STORAGE & VAPORIZATION 1 lot -. LIN Storage Vessel (6ea) (Inner / outer) -. Steam Bath Vaporizer (3ea) -. Nitrogen Pressure Built-up Vaporizer (6ea) - 완료 -. Nitrogen boil off heater (2ea) - 완료 -. Interconnecting piping -. Piping Skid (1set) | G17: 46204 | H17: 0.35 | J17: 최영준 책임 | K17: 고팔라크리스낸 매니저
A18: =ROW()-2 -> 16 | B18: STA4 | C18: 장치 | D18: MS019 | E18: ACTIVATED CARBON FILTER PACKAGE | F18: ACFP (FILTREX SRL) 3 Skid Filter Vessel (Fabtech) 3 EA | G18: 46172 | H18: 0.2 | I18: IRC Filter Vessel 12/22일 발행 완료 / Skid 4/16 발행 예정 | J18: 최영준 책임 | K18: 정진우 책임
A19: =ROW()-2 -> 17 | B19: STA4 | C19: 장치 | D19: MS020 | E19: INCINERATOR PACKAGE | F19: Incinerator Package 1 lot (ZEECO) Chamber & Stack 4 set (Morimatsu) - 완료 Air blower 4 set Burner 2 set - 완료 | G19: 46203 | H19: 0.2 | I19: Skid IRC 발급 기준 / Anchor bolt IRC 발행 완료 / Chamber & Stack STD Flange 수급으로 11월 말 납품가능 | J19: 최영준 책임 | K19: 고팔라크리스낸 매니저
A20: =ROW()-2 -> 18 | B20: STA4 | C20: 장치 | D20: MS021 | E20: FLARE PACKAGE | F20: LPEF 1 lot (ZEECO) MPGF 1 lot (ZEECO) Derrick Structure 1 lot (FMC) Water Seal Drum 1 lot (SAMIF) Dish Head for WSD 2 ea (AOI) Radiation Fence 1 lot (Al Kabii) | G20: 46172 | H20: 0.43 | I20: Stack Riser 7기 모두 IRC 발행 (ZEECO), Derrick Structure IRC 100% (FMC), Derrick 2nd Structure IRC 90% (Al Kaabi), LPEF & MPGF 납기지연 공문 접수 | J20: 최영준 책임 | K20: 고팔라크리스낸 매니저
A21: =ROW()-2 -> 19 | B21: STA4 | C21: 장치 | D21: MS023 | E21: FLARE GAS RECOVERY PACKAGE | F21: FGRP 1 lot Centri. Pump 1 lot Air Cooler 1 lot - 완료 Spearator Vessel 1 lot Motor 1 lot - 완료 | G21: 46266 | H21: 0 | J21: 최영준 책임 | K21: 고팔라크리스낸 매니저
A22: =ROW()-2 -> 20 | B22: STA4 | C22: 장치 | D22: MS024 | E22: EXPLOSION HATCH | G22: 완료 | H22: 1 | I22: IDR 필요없음 / VIRB 제출완료 | J22: 최영준 책임 | K22: 고팔라크리스낸 매니저
A23: =ROW()-2 -> 21 | B23: STA4 | C23: 장치 | D23: MS025 | E23: EQUIPMENT PLATFORM & LADDER | F23: 307.5 MT | G23: 46233 | H23: 0.327 | I23: IDR 필요없음 / VIRB 진행필요 | J23: 고팔라크리스낸 매니저 | K23: 최우석 책임
A24: =ROW()-2 -> 22 | B24: STA4 | C24: 철골 | D24: SS001 | E24: STRUCTURAL STEEL | F24: 22500 MT | G24: 46233 | H24: 0.77 | I24: IDR 작성필요 / VIRB 제출필요 | J24: 고팔라크리스낸 매니저 | K24: 최우석 책임
A25: =ROW()-2 -> 23 | B25: STA4 | C25: 철골 | D25: SC002 | E25: ISOLATED SUPPORT | F25: 2150 MT | G25: 46233 | H25: 0.26 | I25: IDR 필요없음 / VIRB 진행필요없음 | J25: 고팔라크리스낸 매니저 | K25: 최우석 책임
A26: =ROW()-2 -> 24 | B26: STA4 | C26: 회전 | D26: MR001 | E26: CENTRIFUGAL COMPRESSOR (API 617) | F26: CENTRIFUGAL COMPRESSOR (API 617) : 1 ea MOTOR FOR CENTRIFUGAL COMPRESSOR (API 617) : 1 ea Gear Box FOR CENTRIFUGAL COMPRESSOR (API 617) : 1 ea Lube Oil Unit FOR CENTRIFUGAL COMPRESSOR (API 617) : 1 ea | G26: 46172 | H26: 100% 100% 100% 100% | I26: VIRB 진행필요 / IDR 작성필요 | J26: 서민 책임 | K26: 장동철 책임
A27: =ROW()-2 -> 25 | B27: STA4 | C27: 회전 | D27: MR003 | E27: AIR COMPRESSOR PACKAGE (API 672) | F27: AIR COMPRESSOR PACKAGE (API 672) : 4 ea Motor for AIR COMPRESSOR PACKAGE (API 672) : 4 ea | G27: 46172 | H27: 100% 100% | I27: VIRB 진행필요 / IDR 작성필요 | J27: 서민 책임 | K27: 장동철 책임
A28: =ROW()-2 -> 26 | B28: STA4 | C28: 회전 | D28: MR004 | E28: BOILER FEED WATER PUMP (API 610 BB) | F28: BOILER FEED WATER PUMP (API 610 BB) : 3 ea Motor for BOILER FEED WATER PUMP (API 610 BB) : 3 ea | G28: 46172 | H28: 100% 100% | I28: VIRB 진행 중 / IDR 작성 필요 | J28: 서민 책임 | K28: 장동철 책임
A29: =ROW()-2 -> 27 | B29: STA4 | C29: 회전 | D29: MR005 | E29: COOLING WATER PUMP (API 610 BB) | F29: COOLING WATER PUMP (API 610 BB) : 34 ea MOTOR FOR COOLING WATER PUMP (API 610 BB) : 34 ea | G29: 46172 | H29: 100% 100% | I29: VIRB 진행 중 / IDR 작성 필요 | J29: 서민 책임 | K29: 장동철 책임
A30: =ROW()-2 -> 28 | B30: STA4 | C30: 회전 | D30: MR006 | E30: CENTRIFUGAL PUMP (API 610 BB) -BLOW DOWN PUMP | F30: CENTRIFUGAL PUMP (API 610 BB) -Blow Down Pump : 3 ea Motor for CENTRIFUGAL PUMP (API 610 BB) -Blow Down Pump : 3 ea | G30: 46172 | H30: 100% 100% | I30: VIRB 진행필요 / IDR 작성필요 | J30: 서민 책임 | K30: 장동철 책임
A31: =ROW()-2 -> 29 | B31: STA4 | C31: 회전 | D31: MR007 | E31: CENTRIFUGAL PUMP (OH TYPE) | F31: CENTRIFUGAL PUMP (OH TYPE) : 32 ea MOTOR FOR CENTRIFUGAL PUMP (OH TYPE) : 2 ea | G31: 46172 | H31: 100% 100% | I31: VIRB 진행필요 / IDR 작성필요 (Inspection Level 1 item) | J31: 서민 책임 | K31: 장동철 책임
A32: =ROW()-2 -> 30 | B32: STA4 | C32: 회전 | D32: MR007(VO) | E32: CENTRIFUGAL PUMP (OH TYPE) | F32: CENTRIFUGAL PUMP (OH TYPE) : 6 ea | G32: 46172 | H32: 0 | I32: 430-G-0041-A/B, 430-G-0043-A/B, 405-G-0010-A/B 추가됨 | J32: 서민 책임 | K32: 장동철 책임
A33: =ROW()-2 -> 31 | B33: STA4 | C33: 회전 | D33: MR008 | E33: CENTRIFUGAL PUMP (VERTICAL TYPE) | F33: CENTRIFUGAL PUMP (VERTICAL TYPE) : 10 EA | G33: 46386 | H33: 0.6 | I33: 401-G-0001-A/B/C/D 추가됨 | J33: 서민 책임 | K33: 장동철 책임
A34: =ROW()-2 -> 32 | B34: STA4 | C34: 회전 | D34: MR010 | E34: SEALLESS PUMP (API 685) | F34: SEALLESS PUMP (API 685) : 2 ea | G34: 46172 | H34: 1 | I34: Impeller Diameter 문제 확인으로 현재 NCR 발행 및 Waiver Request 제출, Conditional IRC issue, VIRB 진행필요 | J34: 서민 책임 | K34: 장동철 책임
A35: =ROW()-2 -> 33 | B35: STA4 | C35: 회전 | D35: MR010(VO) | E35: SEALLESS PUMP (API 685) | F35: SEALLESS PUMP (API 685) : 2 ea | G35: 46361 | H35: 0.5 | I35: 420-G-0045-A/B 추가 | J35: 서민 책임 | K35: 장동철 책임
A36: =ROW()-2 -> 34 | B36: STA4 | C36: 회전 | D36: MR011 | E36: SUBMERSIBLE PUMP (NON-API) | F36: 29 ea | G36: 46203 | H36: 1 | I36: VIRB 진행필요 / IDR 필요없음(IL 3) Auto Coupling의 adaptor 추가 제작 5월 검사 예정 | J36: 서민 책임 | K36: 장동철 책임
A37: =ROW()-2 -> 35 | B37: STA4 | C37: 회전 | D37: MR012 | E37: FIRE WATER PUMP (NFPA 20) | F37: FIRE WATER PUMP (NFPA 20) : 9 ea MOTOR FOR FIRE WATER PUMP (NFPA 20) : 3 ea | G37: 46172 | H37: 100% 100% | I37: VIRB 완료, IDR 작성 필요 | J37: 서민 책임 | K37: 장동철 책임
A38: =ROW()-2 -> 36 | B38: STA4 | C38: 회전 | D38: MR013 | E38: COOLING TOWER | F38: COOLING TOWER : 1 ea Motor for COOLING TOWER : 54 ea | G38: 46172 | H38: 1 | I38: VIRB 진행필요 / IDR 작성필요 | J38: 서민 책임 | K38: 장동철 책임
A39: =ROW()-2 -> 37 | B39: STA4 | C39: 회전 | D39: MR014 | E39: ELECTROCHLORINATION PACKAGE | F39: ELECTROCHLORINATION PACKAGE : 9 ea | G39: 46203 | H39: 0.95 | I39: Platform, Pipe Supports and cable tray supports 제작중 | J39: 서민 책임 | K39: 장동철 책임
A40: =ROW()-2 -> 38 | B40: STA4 | C40: 회전 | D40: MR015 | E40: CHILLER PACKAGE | F40: 2 ea | G40: 46142 | H40: 1 | I40: IAP 없음(IL3), VIRB 진행필요 / IDR 필요없음(IL 3) | J40: 서민 책임 | K40: 장동철 책임
A41: =ROW()-2 -> 39 | B41: STA4 | C41: 회전 | D41: MR016 | E41: CHEMICAL INJECTION PACKAGE | F41: CHEMICAL INJECTION PACKAGE : 5 ea | G41: 46172 | H41: 0 | J41: 서민 책임 | K41: 장동철 책임
A42: =ROW()-2 -> 40 | B42: STA4 | C42: 회전 | D42: MR017 | E42: CRANE | F42: 9 ea | G42: 46172 | H42: 1 | I42: IAP 없음(IL3), VIRB 진행 중 / IDR 필요없음(IL 3) | J42: 서민 책임 | K42: 장동철 책임
A43: =ROW()-2 -> 41 | B43: STA4 | C43: 회전 | D43: MR019 | E43: SIDE ENTRY MIXER | F43: 2 ea | G43: 46341 | H43: 0 | I43: 추가 PO(KOM 완료) | J43: 서민 책임 | K43: 장동철 책임
A44: =ROW()-2 -> 42 | B44: STA4 | C44: 회전 | D44: MR020 | E44: SEA WATER BOOSER PUMP | F44: 4 ea | G44: 46349 | H44: 0 | I44: 추가 PO(KOM 완료) | J44: 서민 책임 | K44: 장동철 책임
A45: =ROW()-2 -> 43 | B45: STA4 | C45: 소방/안전 | D45: SE001 | E45: FIRE & SAFETY EQUIPMENT | F45: 1 lot | G45: 46172 | H45: 0.9 | I45: IAP 없음(IL3) | J45: 서민 책임 | K45: 장동철 책임
A46: =ROW()-2 -> 44 | B46: STA4 | C46: 소방/안전 | D46: SE002 | E46: CLEAN AGENT FIRE EXTINGUISHING SYSTEM | F46: 1 lot | G46: 46172 | H46: 0.9 | I46: IAP 없음(IL3) | J46: 서민 책임 | K46: 장동철 책임
A47: =ROW()-2 -> 45 | B47: STA4 | C47: 공조 | D47: HV001 | E47: HVAC EQUIPMENT | F47: 1 lot | G47: 46172 | H47: 0.9 | I47: IAP 없음(IL3) | J47: 서민 책임 | K47: 장동철 책임
A48: =ROW()-2 -> 46 | B48: STA4 | C48: 기타 | D48: PR001 | E48: CHEMICAL | G48: NA | H48: NA | I48: Non inspectable | J48: 서민 책임 | K48: 장동철 책임
A49: =ROW()-2 -> 47 | B49: STA4 | C49: 기타 | D49: PR002 | E49: SPECIAL CHEMICAL | G49: NA | H49: NA | I49: Non inspectable | J49: 서민 책임 | K49: 장동철 책임
A50: =ROW()-2 -> 48 | B50: STA4 | C50: 배관 | D50: PI001 | E50: RTR PIPING | F50: 117200 m | G50: 46357 | H50: 0.96 | J50: 임효원 책임 | K50: 최우석 책임
A51: =ROW()-2 -> 49 | B51: STA4 | C51: 배관 | D51: PI002 | E51: CPVC PIPING AND VALVE | F51: 24973 ea, 6465 ea | G51: 46143 | H51: 0.99 | I51: 2개 PO 분리 발주, VIRB 접수 필요 (IL 3) , IDR 필요없음 | J51: 임효원 책임 | K51: 최우석 책임
A52: =ROW()-2 -> 50 | B52: STA4 | C52: 배관 | D52: PI003 | E52: CARBON STEEL SMLS PIPE | F52: 271874 m | G52: 46204 | H52: 0.95 | J52: 임효원 책임 | K52: 최우석 책임
A53: =ROW()-2 -> 51 | B53: STA4 | C53: 배관 | D53: PI004 | E53: CARBON STEEL WELDED PIPE | F53: 29616 m | G53: 46204 | H53: 0.99 | J53: 임효원 책임 | K53: 최우석 책임
A54: =ROW()-2 -> 52 | B54: STA4 | C54: 배관 | D54: PI005 | E54: STAINLESS STEEL SMLS PIPE | F54: 16230 m | G54: 46204 | H54: 0.98 | J54: 임효원 책임 | K54: 최우석 책임
A55: =ROW()-2 -> 53 | B55: STA4 | C55: 배관 | D55: PI006 | E55: STAINLESS STEEL WELDED PIPE | F55: 4440 m | G55: 완료 | H55: 1 | I55: IDR 체출완료 / VIRB 제출완료 | J55: 임효원 책임 | K55: 최우석 책임
A56: =ROW()-2 -> 54 | B56: STA4 | C56: 배관 | D56: PI007 | E56: LOW ALLOY STEEL SMLS PIPE | F56: 402 m | G56: 완료 | H56: 1 | I56: IDR 체출완료 / VIRB 제출완료 | J56: 임효원 책임 | K56: 최우석 책임
A57: =ROW()-2 -> 55 | B57: STA4 | C57: 배관 | D57: PI008 | E57: LOW ALLOY STEEL WELDED PIPE | F57: 600 m | G57: 완료 | H57: 1 | I57: IDR 체출완료 / VIRB 제출완료 | J57: 임효원 책임 | K57: 최우석 책임
A58: =ROW()-2 -> 56 | B58: STA4 | C58: 배관 | D58: PI009 | E58: FORGED FITTING | F58: 47491 ea | G58: 46174 | H58: 0.95 | J58: 임효원 책임 | K58: 최우석 책임
A59: =ROW()-2 -> 57 | B59: STA4 | C59: 배관 | D59: PI010 | E59: WROUGHT FITTING | F59: 18862 ea, 9418 ea | G59: 46174 | H59: 0.98 | I59: 2개 PO 분리 발주 | J59: 임효원 책임 | K59: 최우석 책임
A60: =ROW()-2 -> 58 | B60: STA4 | C60: 배관 | D60: PI011 | E60: FABRICATED FITTING (LATERAL) | F60: 24 ea | G60: 완료 | H60: 1 | I60: IDR 체출완료 / VIRB 제출완료 | J60: 임효원 책임 | K60: 최우석 책임
A61: =ROW()-2 -> 59 | B61: STA4 | C61: 배관 | D61: PI012 | E61: FLANGE | F61: 47427 ea, 818 ea, 134 ea | G61: 46235 | H61: 0.9 | I61: 3개 PO 분리 발주, 1건 IDR 제출 완료 | J61: 임효원 책임 | K61: 최우석 책임
A62: =ROW()-2 -> 60 | B62: STA4 | C62: 배관 | D62: PI013 | E62: FIRE WATER VALVE | F62: 1079 ea, 39 ea | G62: 46174 | H62: 1 | I62: 2개 PO 분리 발주, 1건 IDR 제출 완료 | J62: 임효원 책임 | K62: 최우석 책임
A63: =ROW()-2 -> 61 | B63: STA4 | C63: 배관 | D63: PI014 | E63: FORGED VALVE | F63: 9780 ea | G63: 46357 | H63: 0.96 | J63: 임효원 책임 | K63: 최우석 책임
A64: =ROW()-2 -> 62 | B64: STA4 | C64: 배관 | D64: PI015 | E64: DIAPHRAGM VALVE | F64: 909 ea | G64: 46174 | H64: 0.93 | I64: IDR 필요없음 / VIRB 진행필요 | J64: 임효원 책임 | K64: 최우석 책임
A65: =ROW()-2 -> 63 | B65: STA4 | C65: 배관 | D65: PI016 | E65: CASTING VALVE | F65: 2567 ea, 9 ea | G65: 46296 | H65: 0.9 | I65: 2개 PO 분리 발주 | J65: 임효원 책임 | K65: 최우석 책임
A66: =ROW()-2 -> 64 | B66: STA4 | C66: 배관 | D66: PI017 | E66: DUCTILE IRON EPOXY LINED VALVE | F66: 800 ea, 12 ea | G66: 46235 | H66: 0.9 | I66: 2개 PO 분리 발주 | J66: 임효원 책임 | K66: 최우석 책임
A67: =ROW()-2 -> 65 | B67: STA4 | C67: 배관 | D67: PI018 | E67: BUTTERFLY VALVE | F67: 595 ea, 18 ea | G67: 46357 | H67: 0.9 | I67: 2개 PO 분리 발주 | J67: 임효원 책임 | K67: 최우석 책임
A68: =ROW()-2 -> 66 | B68: STA4 | C68: 배관 | D68: PI019 | E68: BALL VALVE | F68: 211 ea, 50 ea | G68: 46357 | H68: 0.95 | I68: 2개 PO 분리 발주, 1건 IDR 제출 완료 | J68: 임효원 책임 | K68: 최우석 책임
A69: =ROW()-2 -> 67 | B69: STA4 | C69: 배관 | D69: PI021 | E69: DUAL PLATE CHECK VALVE | F69: 167 ea | G69: 46174 | H69: 0.79 | J69: 임효원 책임 | K69: 최우석 책임
A70: =ROW()-2 -> 68 | B70: STA4 | C70: 배관 | D70: PI022 | E70: PLUG VALVE | F70: 217 ea, 20 ea | G70: 46296 | H70: 0.75 | I70: 2개 PO 분리 발주 | J70: 임효원 책임 | K70: 최우석 책임
A71: =ROW()-2 -> 69 | B71: STA4 | C71: 배관 | D71: PI023 | E71: BRONZE VALVE | F71: 160 ea, 10 ea | G71: 46235 | H71: 0.9 | I71: 2개 PO 분리 발주 | J71: 임효원 책임 | K71: 최우석 책임
A72: =ROW()-2 -> 70 | B72: STA4 | C72: 배관 | D72: PI024 | E72: AXIAL CHECK VALVE | F72: 2 ea | G72: 완료 | H72: 1 | I72: IDR 체출완료 / VIRB 제출완료 | J72: 임효원 책임 | K72: 최우석 책임
A73: =ROW()-2 -> 71 | B73: STA4 | C73: 배관 | D73: PI025 | E73: GASKET AND INSULATION KIT | F73: 55660 ea | G73: 46296 | H73: 0.95 | I73: VIRB 접수 필요, IDR 작성/제출 불 필요 (inspection level 3) | J73: 임효원 책임 | K73: 최우석 책임
A74: =ROW()-2 -> 72 | B74: STA4 | C74: 배관 | D74: PI026 | E74: BOLT AND NUT | F74: 350415 ea | G74: 46296 | H74: 0.8 | I74: VIRB 접수 필요, IDR 작성/제출 불 필요 (inspection level 3) | J74: 임효원 책임 | K74: 최우석 책임
A75: =ROW()-2 -> 73 | B75: STA4 | C75: 배관 | D75: PI027 | E75: STEAM TRAP AND MANIFOLD | F75: 366 ea | G75: 46174 | H75: 0 | I75: VIRB 접수 필요, IDR 작성/제출 불 필요 (inspection level 3) | J75: 임효원 책임 | K75: 최우석 책임
A76: =ROW()-2 -> 74 | B76: STA4 | C76: 배관 | D76: PI028 | E76: STRAINER | F76: 247 ea | G76: 완료 | H76: 1 | I76: IDR 체출완료 / VIRB 제출완료 | J76: 임효원 책임 | K76: 최우석 책임
A77: =ROW()-2 -> 75 | B77: STA4 | C77: 배관 | D77: PI029 | E77: HOSE AND CONNECTOR | F77: 533 ea | G77: 46143 | H77: 0.8 | I77: VIRB 접수 필요, IDR 작성/제출 불 필요 (inspection level 3) | J77: 임효원 책임 | K77: 최우석 책임
A78: =ROW()-2 -> 76 | B78: STA4 | C78: 배관 | D78: PI030 | E78: EXPANSION JOINT | F78: 124 ea | G78: 46174 | H78: 0.95 | J78: 임효원 책임 | K78: 최우석 책임
A79: =ROW()-2 -> 77 | B79: STA4 | C79: 배관 | D79: PI031 | E79: INJECTION NOZZLE | F79: 2 ea | G79: 완료 | H79: 1 | I79: VIRB 제출완료, IDR 작성/제출 불 필요 (inspection level 3) | J79: 임효원 책임 | K79: 최우석 책임
A80: =ROW()-2 -> 78 | B80: STA4 | C80: 배관 | D80: PI032 | E80: FBE LINED AND COATED PIPING | F80: 9238 | G80: 46235 | H80: 0.75 | J80: 임효원 책임 | K80: 최우석 책임
A81: =ROW()-2 -> 79 | B81: STA4 | C81: 배관 | D81: PI033 | E81: INTERLOCKING SYSTEM | F81: 73 | G81: 46174 | H81: 0 | I81: VIRB 접수 필요, IDR 작성/제출 불 필요 (inspection level 3) | J81: 임효원 책임 | K81: 최우석 책임
A82: =ROW()-2 -> 80 | B82: STA4 | C82: 배관 | D82: PI034 | E82: TUBE AND TUBE FITTING | F82: 22963, 4326 | G82: 46143 | H82: 1 | I82: VIRB 접수 필요, IDR 작성/제출 불 필요 (inspection level 3) | J82: 임효원 책임 | K82: 최우석 책임
A83: =ROW()-2 -> 81 | B83: STA4 | C83: 배관 | D83: PI036 | E83: SPRING (INCL. COLD SUPPORT) | F83: 1734 ea | G83: 46143 | H83: 0.95 | I83: VIRB 접수 필요, IDR 작성/제출 불 필요 (inspection level 3) | J83: 임효원 책임 | K83: 최우석 책임
A84: =ROW()-2 -> 82 | B84: STA4 | C84: 배관 | D84: PI037 | E84: PARALLEL SLIDE GATE VALVE (BULK) | F84: 44 ea | G84: 46296 | H84: 0.93 | J84: 임효원 책임 | K84: 최우석 책임
A85: =ROW()-2 -> 83 | B85: STA4 | C85: 배관 | D85: PI038 | E85: KNIFE GATE VALVE | F85: 69 ea | G85: 46174 | H85: 0.96 | J85: 임효원 책임 | K85: 최우석 책임
A86: =ROW()-2 -> 84 | B86: STA4 | C86: 배관 | D86: PI039 | E86: SPECIAL FITTING (BULK) | F86: 39 ea | G86: 완료 | H86: 1 | I86: IDR 체출완료 / VIRB 제출완료 | J86: 임효원 책임 | K86: 최우석 책임
A87: =ROW()-2 -> 85 | B87: STA4 | C87: 배관 | D87: PI040 | E87: AIR RELEASE VALVE | F87: 42 ea | G87: 완료 | H87: 1 | I87: VIRB 제출완료, IDR 작성/제출 불 필요 (inspection level 3) | J87: 임효원 책임 | K87: 최우석 책임
A88: =ROW()-2 -> 86 | B88: STA4 | C88: 전기 | D88: EL001 | E88: 230KV GIS | F88: 14 bays | G88: 46143 | H88: 1 | I88: LV.2 / IDR 제출 완료 / VIRB 진행 중 | J88: 윤희수 책임 | K88: 강인묵 책임
A89: =ROW()-2 -> 87 | B89: STA4 | C89: 전기 | D89: EL002 | E89: 230/34.5KV POWER TRANSFORMER | F89: 6대 | G89: 완료 | H89: 1 | I89: LV.2 / IDR 제출 완료 / VIRB 제출 완료 | J89: 윤희수 책임 | K89: 강인묵 책임
A90: =ROW()-2 -> 88 | B90: STA4 | C90: 전기 | D90: EL003 | E90: 230KV CABLE & ACCESSORIES | F90: 9,585 m | G90: 완료 | H90: 1 | I90: LV.2 / IDR 제출 완료 / VIRB 제출 완료 | J90: 윤희수 책임 | K90: 강인묵 책임
A91: =ROW()-2 -> 89 | B91: STA4 | C91: 전기 | D91: EL004 | E91: POWER TRANSFORMER & NGR | F91: 68대 | G91: 46143 | H91: 1 | I91: LV.2 / IDR 작성 중 / VIRB 진행 필요 | J91: 이해석 책임 | K91: 강인묵 책임
A92: =ROW()-2 -> 90 | B92: STA4 | C92: 전기 | D92: EL005 | E92: POWER CAPACITOR | F92: 6대 | G92: 46143 | H92: 1 | I92: LV.2 / IDR 제출 완료 / VIRB 독려중 | J92: 이해석 책임 | K92: 강인묵 책임
A93: =ROW()-2 -> 91 | B93: STA4 | C93: 전기 | D93: EL006 | E93: HV SWGR (34.5KV) HV SWGR/MCC | F93: 5 sets | G93: 46143 | H93: 1 | I93: LV.2 / IDR 작성 중 / VIRB 독려중 | J93: 윤희수 책임 | K93: 강인묵 책임
A94: =ROW()-2 -> 92 | B94: STA4 | C94: 전기 | D94: EL007 | E94: HV SWGR (13.8KV & 4.16KV) HV CONTROL GEAR | F94: 9 sets | G94: 46143 | H94: 1 | I94: LV.2 / IDR 작성 중 / VIRB 독려중 / NCR 종결 필요 | J94: 이해석 책임 | K94: 강인묵 책임
A95: =ROW()-2 -> 93 | B95: STA4 | C95: 전기 | D95: EL008 | E95: LV SWGR | F95: 12 sets | G95: 46143 | H95: 1 | I95: LV.2 / IDR 작성 중 / VIRB 독려중 / NCR 종결 필요 | J95: 이해석 책임 | K95: 강인묵 책임
A96: =ROW()-2 -> 94 | B96: STA4 | C96: 전기 | D96: EL009 | E96: LV CONTROLGEAR | F96: 22 sets | G96: 46143 | H96: 1 | I96: LV.2 / IDR 작성 중 / VIRB 독려중 / NCR 종결 필요 | J96: 이해석 책임 | K96: 강인묵 책임
A97: =ROW()-2 -> 95 | B97: STA4 | C97: 전기 | D97: EL010 | E97: EMERGENCY DIESEL GENERATOR | F97: 4 sets | G97: 46143 | H97: 1 | I97: LV.3 / IDR 불필요 / VIRB 진행 필요 | J97: 윤희수 책임 | K97: 강인묵 책임
A98: =ROW()-2 -> 96 | B98: STA4 | C98: 전기 | D98: EL011 | E98: AC UPS & DC SYSTEM | F98: 58 sets | G98: 46143 | H98: 1 | I98: LV.2 / IDR 제출 완료 / VIRB 독려중 | J98: 이해석 책임 | K98: 강인묵 책임
A99: =ROW()-2 -> 97 | B99: STA4 | C99: 전기 | D99: EL012 | E99: ELECTRICAL CONTROL SYSTEM (ECS) | F99: 8 sets | G99: 46143 | H99: 1 | I99: LV.2 / IDR 작성 중 / VIRB 진행 필요 / NCR 종결 필요 | J99: 강인묵 책임 | K99: 윤희수 책임
A100: =ROW()-2 -> 98 | B100: STA4 | C100: 전기 | D100: EL012-1 | E100: Power Monitoring System (PMS) | F100: 12 sets | G100: 46143 | H100: 1 | I100: LV.2 / EL012 ECS 와 동시 진행 예정 | J100: 윤희수 책임 | K100: 강인묵 책임
...

Sheet 출장현황
A1: 출장자 | B1: 출장목적 | C1: 프로젝트 | D1: 품목 | E1: 방문업체 | F1: 국가 | G1: 출발일 | H1: 복귀일
A2: 석우경 매니저 | B2: FAT | C2: VEQU | D2: ID FAN | E2: TLT TURBO | F2: 중국 | G2: 45662 | H2: 45668
A3: 최영준 책임 | B3: PIM | C3: STA4 | D3: INCINERATOR - CHAMBER & STACK | E3: MORIMATSU | F3: 중국 | G3: 45663 | H3: 45666
A4: 이해석 책임 | B4: FAT | C4: SHN1 | D4: AC,DC UPS | E4: GUTOR | F4: 말레이시아 | G4: 45676 | H4: 45680
A5: 강택기 책임 | B5: PIM | C5: STA4 | D5: ON-OFF VALVE BUTTERFLY | E5: IMI | F5: 사우디아라비아 | G5: 45677 | H5: 45678
A6: 최종현 책임 | B6: PIM | C6: SAC2 | D6: ANALYZER SYSTEM | E6: ABB | F6: 사우디아라비아 | G6: 45677 | H6: 45681
A7: 서민 책임 | B7: PIM | C7: STA4 | D7: CHEMICAL INJECTION PKG | E7: SAUDI WELLS | F7: 사우디아라비아 | G7: 45678 | H7: 45681
A8: 강택기 책임 | B8: PIM | C8: STA4 | D8: ON-OFF VALVE GATE | E8: L&T VALVE | F8: 사우디아라비아 | G8: 45679 | H8: 45680
A9: 정진우 책임 | B9: PIM | C9: STA4 | D9: FLARE PKG - DERRICK STURCTURE | E9: DSD-FERROMETALCO | F9: 이집트 | G9: 45680 | H9: 45682
A10: 정진우 책임 | B10: PIM | C10: STA4 | D10: FLARE PKG - MPGF | E10: ZEECO MIDDLE EAST | F10: 사우디아라비아 | G10: 45691 | H10: 45695
A11: 최우석 책임 | B11: PIM | C11: STA4 | D11: FLARE PKG - MPGF | E11: ZEECO MIDDLE EAST | F11: 사우디아라비아 | G11: 45691 | H11: 45695
A12: 정진우 책임 | B12: PIM | C12: STA4 | D12: INCINERATOR PKG - BURNER & SKID | E12: ZEECO MIDDLE EAST | F12: 사우디아라비아 | G12: 45691 | H12: 45695
A13: 최우석 책임 | B13: PIM | C13: STA4 | D13: INCINERATOR PKG - BURNER & SKID | E13: ZEECO MIDDLE EAST | F13: 사우디아라비아 | G13: 45691 | H13: 45695
... A89: 강태준 책임 | B89: 업체실사 | C89: CSSP | D89: SPOOL FABRICATION & EXTERNAL/INTERNAL COATING | E89: 주성이엔지 | F89: 대한민국 | G89: 46086 | H89: 46086

Sheet 주요현안
A1: Title | B1: Owner | C1: Project_Code | D1: Action_Required
A2: Knife Gate Valve 표면 처리불량 | B2: 임효원 책임 | C2: STA4 | D2: FBE 작업 진행 중
A3: N2 Receiver 폭발 사고 관련 추가 제작 Item 검사 절차 협의 | B3: 장동철 책임 | C3: SM12 | D3: SVL & Inspection Level 협의 중 (SAIR)
A4: Produced Water Booster Pump 관련 Casing 파손 | B4: 서민 책임 | C4: MIP6 | D4: 결함 판독을 위해 현장에서 RT 수행 예정
A5: N2 Generation Package 성능 미달 | B5: 장동철 책임 | C5: IBRU | D5: 제작 및 검사 진행 중
A6: Bypass Valve 현장시험 불합격 | B6: 석우경 매니저 | C6: VEQU
A7: LV Switchgear 내부 부식 발생 | B7: 윤희수 책임 | C7: ALOM | D7: 재제작 진행 중 (5월말 FAT 예상)
A8: 원소재 성적서 검토 시스템 | B8: 장동철 책임 | C8: 플랜트구매품질팀 | D8: 경영분석팀 & IT지원팀 협의 중
A9: Punch 관리방법 개선 | B9: 이해석 책임 | C9: 플랜트구매품질팀 | D9: 추진안 준비 중
A10: TPA Workshop | B10: 장동철 책임 | C10: 플랜트구매품질팀 | D10: 금주 중 참석자 확정 및 사전 설문 완료 예정
A11: TPA 실행 비용 분석 및 입찰 예산 적정성 검증 | B11: 강태준 책임 | C11: 플랜트구매품질팀 | D11: 프로젝트별 TPA 청산자료 1차 가공 완료
